<?xml version='1.0' encoding='utf-8'?>
<SHOP>
  <SHOPITEM><CODE>MK0694</CODE><CURRENCY>CZK</CURRENCY><PRICE>4905</PRICE><FLAGS><FLAG><CODE>posledni-kus</CODE><ACTIVE>0</ACTIVE></FLAG><FLAG><CODE>trhem-overena-cena</CODE><ACTIVE>0</ACTIVE></FLAG></FLAGS> <STOCK><AMOUNT>5</AMOUNT></STOCK><INFORMATION_PARAMETERS><INFORMATION_PARAMETER><NAME>Výkupní cena</NAME><VALUE>4 580 Kč</VALUE></INFORMATION_PARAMETER></INFORMATION_PARAMETERS><HEUREKA_HIDDEN>1</HEUREKA_HIDDEN><ZBOZI_HIDDEN>1</ZBOZI_HIDDEN><AVAILABILITY_IN_STOCK>Skladem</AVAILABILITY_IN_STOCK><FREE_SHIPPING>0</FREE_SHIPPING></SHOPITEM>
  <SHOPITEM><CODE>MK0695</CODE><CURRENCY>CZK</CURRENCY><PRICE>10953</PRICE><FLAGS><FLAG><CODE>posledni-kus</CODE><ACTIVE>0</ACTIVE></FLAG><FLAG><CODE>trhem-overena-cena</CODE><ACTIVE>0</ACTIVE></FLAG></FLAGS> <STOCK><AMOUNT>25</AMOUNT></STOCK><INFORMATION_PARAMETERS><INFORMATION_PARAMETER><NAME>Výkupní cena</NAME><VALUE>10 157 Kč</VALUE></INFORMATION_PARAMETER></INFORMATION_PARAMETERS><HEUREKA_HIDDEN>1</HEUREKA_HIDDEN><ZBOZI_HIDDEN>1</ZBOZI_HIDDEN><AVAILABILITY_IN_STOCK>Dodání 5-10 dní</AVAILABILITY_IN_STOCK><FREE_SHIPPING>0</FREE_SHIPPING></SHOPITEM>
  <SHOPITEM><CODE>MK0696</CODE><CURRENCY>CZK</CURRENCY><PRICE>26748</PRICE><FLAGS><FLAG><CODE>posledni-kus</CODE><ACTIVE>0</ACTIVE></FLAG><FLAG><CODE>trhem-overena-cena</CODE><ACTIVE>0</ACTIVE></FLAG></FLAGS> <STOCK><AMOUNT>5</AMOUNT></STOCK><INFORMATION_PARAMETERS><INFORMATION_PARAMETER><NAME>Výkupní cena</NAME><VALUE>25 374 Kč</VALUE></INFORMATION_PARAMETER></INFORMATION_PARAMETERS><HEUREKA_HIDDEN>1</HEUREKA_HIDDEN><ZBOZI_HIDDEN>1</ZBOZI_HIDDEN><AVAILABILITY_IN_STOCK>Dodání 5-10 dní</AVAILABILITY_IN_STOCK><FREE_SHIPPING>0</FREE_SHIPPING></SHOPITEM>
  <SHOPITEM><CODE>MK0697</CODE><CURRENCY>CZK</CURRENCY><PRICE>52672</PRICE><FLAGS><FLAG><CODE>posledni-kus</CODE><ACTIVE>0</ACTIVE></FLAG><FLAG><CODE>trhem-overena-cena</CODE><ACTIVE>0</ACTIVE></FLAG></FLAGS> <STOCK><AMOUNT>5</AMOUNT></STOCK><INFORMATION_PARAMETERS><INFORMATION_PARAMETER><NAME>Výkupní cena</NAME><VALUE>51 153 Kč</VALUE></INFORMATION_PARAMETER></INFORMATION_PARAMETERS><HEUREKA_HIDDEN>1</HEUREKA_HIDDEN><ZBOZI_HIDDEN>1</ZBOZI_HIDDEN><AVAILABILITY_IN_STOCK>Dodání 5-10 dní</AVAILABILITY_IN_STOCK><FREE_SHIPPING>1</FREE_SHIPPING></SHOPITEM>
  <SHOPITEM><CODE>MK0698</CODE><CURRENCY>CZK</CURRENCY><PRICE>101599</PRICE><FLAGS><FLAG><CODE>posledni-kus</CODE><ACTIVE>0</ACTIVE></FLAG><FLAG><CODE>trhem-overena-cena</CODE><ACTIVE>0</ACTIVE></FLAG></FLAGS> <STOCK><AMOUNT>103</AMOUNT></STOCK><INFORMATION_PARAMETERS><INFORMATION_PARAMETER><NAME>Výkupní cena</NAME><VALUE>98 505 Kč</VALUE></INFORMATION_PARAMETER></INFORMATION_PARAMETERS><HEUREKA_HIDDEN>1</HEUREKA_HIDDEN><ZBOZI_HIDDEN>1</ZBOZI_HIDDEN><AVAILABILITY_IN_STOCK>Skladem</AVAILABILITY_IN_STOCK><FREE_SHIPPING>1</FREE_SHIPPING></SHOPITEM>
  <SHOPITEM><CODE>MK0741</CODE><CURRENCY>CZK</CURRENCY><PRICE>5441</PRICE><FLAGS><FLAG><CODE>posledni-kus</CODE><ACTIVE>0</ACTIVE></FLAG><FLAG><CODE>trhem-overena-cena</CODE><ACTIVE>0</ACTIVE></FLAG></FLAGS> <STOCK><AMOUNT>5</AMOUNT></STOCK><INFORMATION_PARAMETERS><INFORMATION_PARAMETER><NAME>Výkupní cena</NAME><VALUE>3 869 Kč</VALUE></INFORMATION_PARAMETER></INFORMATION_PARAMETERS><HEUREKA_HIDDEN>1</HEUREKA_HIDDEN><ZBOZI_HIDDEN>1</ZBOZI_HIDDEN><AVAILABILITY_IN_STOCK>Dodání 5-10 dní</AVAILABILITY_IN_STOCK><FREE_SHIPPING>0</FREE_SHIPPING></SHOPITEM>
  <SHOPITEM><CODE>MK0771</CODE><CURRENCY>CZK</CURRENCY><PRICE>5174</PRICE><FLAGS><FLAG><CODE>posledni-kus</CODE><ACTIVE>0</ACTIVE></FLAG><FLAG><CODE>trhem-overena-cena</CODE><ACTIVE>0</ACTIVE></FLAG></FLAGS> <STOCK><AMOUNT>237</AMOUNT></STOCK><INFORMATION_PARAMETERS><INFORMATION_PARAMETER><NAME>Výkupní cena</NAME><VALUE>4 826 Kč</VALUE></INFORMATION_PARAMETER></INFORMATION_PARAMETERS><HEUREKA_HIDDEN>1</HEUREKA_HIDDEN><ZBOZI_HIDDEN>1</ZBOZI_HIDDEN><AVAILABILITY_IN_STOCK>Skladem</AVAILABILITY_IN_STOCK><FREE_SHIPPING>0</FREE_SHIPPING></SHOPITEM>
  <SHOPITEM><CODE>MK0769</CODE><CURRENCY>CZK</CURRENCY><PRICE>11356</PRICE><FLAGS><FLAG><CODE>posledni-kus</CODE><ACTIVE>0</ACTIVE></FLAG><FLAG><CODE>trhem-overena-cena</CODE><ACTIVE>1</ACTIVE></FLAG></FLAGS> <STOCK><AMOUNT>236</AMOUNT></STOCK><INFORMATION_PARAMETERS><INFORMATION_PARAMETER><NAME>Výkupní cena</NAME><VALUE>10 777 Kč</VALUE></INFORMATION_PARAMETER></INFORMATION_PARAMETERS><HEUREKA_HIDDEN>0</HEUREKA_HIDDEN><ZBOZI_HIDDEN>0</ZBOZI_HIDDEN><AVAILABILITY_IN_STOCK>Dodání 5-10 dní</AVAILABILITY_IN_STOCK><FREE_SHIPPING>0</FREE_SHIPPING></SHOPITEM>
  <SHOPITEM><CODE>MK0772</CODE><CURRENCY>CZK</CURRENCY><PRICE>27577</PRICE><FLAGS><FLAG><CODE>posledni-kus</CODE><ACTIVE>0</ACTIVE></FLAG><FLAG><CODE>trhem-overena-cena</CODE><ACTIVE>1</ACTIVE></FLAG></FLAGS> <STOCK><AMOUNT>151</AMOUNT></STOCK><INFORMATION_PARAMETERS><INFORMATION_PARAMETER><NAME>Výkupní cena</NAME><VALUE>26 374 Kč</VALUE></INFORMATION_PARAMETER></INFORMATION_PARAMETERS><HEUREKA_HIDDEN>0</HEUREKA_HIDDEN><ZBOZI_HIDDEN>0</ZBOZI_HIDDEN><AVAILABILITY_IN_STOCK>Dodání 5-10 dní</AVAILABILITY_IN_STOCK><FREE_SHIPPING>0</FREE_SHIPPING></SHOPITEM>
  <SHOPITEM><CODE>MK0770</CODE><CURRENCY>CZK</CURRENCY><PRICE>53469</PRICE><FLAGS><FLAG><CODE>posledni-kus</CODE><ACTIVE>0</ACTIVE></FLAG><FLAG><CODE>trhem-overena-cena</CODE><ACTIVE>1</ACTIVE></FLAG></FLAGS> <STOCK><AMOUNT>88</AMOUNT></STOCK><INFORMATION_PARAMETERS><INFORMATION_PARAMETER><NAME>Výkupní cena</NAME><VALUE>51 638 Kč</VALUE></INFORMATION_PARAMETER></INFORMATION_PARAMETERS><HEUREKA_HIDDEN>0</HEUREKA_HIDDEN><ZBOZI_HIDDEN>0</ZBOZI_HIDDEN><AVAILABILITY_IN_STOCK>Dodání 5-10 dní</AVAILABILITY_IN_STOCK><FREE_SHIPPING>1</FREE_SHIPPING></SHOPITEM>
  <SHOPITEM><CODE>MK0768</CODE><CURRENCY>CZK</CURRENCY><PRICE>102495</PRICE><FLAGS><FLAG><CODE>posledni-kus</CODE><ACTIVE>0</ACTIVE></FLAG><FLAG><CODE>trhem-overena-cena</CODE><ACTIVE>1</ACTIVE></FLAG></FLAGS> <STOCK><AMOUNT>164</AMOUNT></STOCK><INFORMATION_PARAMETERS><INFORMATION_PARAMETER><NAME>Výkupní cena</NAME><VALUE>100 402 Kč</VALUE></INFORMATION_PARAMETER></INFORMATION_PARAMETERS><HEUREKA_HIDDEN>0</HEUREKA_HIDDEN><ZBOZI_HIDDEN>0</ZBOZI_HIDDEN><AVAILABILITY_IN_STOCK>Dodání 5-10 dní</AVAILABILITY_IN_STOCK><FREE_SHIPPING>1</FREE_SHIPPING></SHOPITEM>
  <SHOPITEM><CODE>MK0815</CODE><CURRENCY>CZK</CURRENCY><PRICE>100428</PRICE><STANDARD_PRICE>103480</STANDARD_PRICE><FLAGS><FLAG><CODE>posledni-kus</CODE><ACTIVE>0</ACTIVE></FLAG><FLAG><CODE>trhem-overena-cena</CODE><ACTIVE>0</ACTIVE></FLAG></FLAGS> <STOCK><AMOUNT>5</AMOUNT></STOCK><INFORMATION_PARAMETERS><INFORMATION_PARAMETER><NAME>Výkupní cena</NAME><VALUE>75 488 Kč</VALUE></INFORMATION_PARAMETER></INFORMATION_PARAMETERS><HEUREKA_HIDDEN>1</HEUREKA_HIDDEN><ZBOZI_HIDDEN>1</ZBOZI_HIDDEN><AVAILABILITY_IN_STOCK>Dodání 5-10 dní</AVAILABILITY_IN_STOCK><FREE_SHIPPING>1</FREE_SHIPPING></SHOPITEM>
  <SHOPITEM><CODE>MK0814</CODE><CURRENCY>CZK</CURRENCY><PRICE>221512</PRICE><STANDARD_PRICE>227120</STANDARD_PRICE><FLAGS><FLAG><CODE>posledni-kus</CODE><ACTIVE>0</ACTIVE></FLAG><FLAG><CODE>trhem-overena-cena</CODE><ACTIVE>0</ACTIVE></FLAG></FLAGS> <STOCK><AMOUNT>11</AMOUNT></STOCK><INFORMATION_PARAMETERS><INFORMATION_PARAMETER><NAME>Výkupní cena</NAME><VALUE>194 878 Kč</VALUE></INFORMATION_PARAMETER></INFORMATION_PARAMETERS><HEUREKA_HIDDEN>1</HEUREKA_HIDDEN><ZBOZI_HIDDEN>1</ZBOZI_HIDDEN><AVAILABILITY_IN_STOCK>Dodání 5-10 dní</AVAILABILITY_IN_STOCK><FREE_SHIPPING>1</FREE_SHIPPING></SHOPITEM>
  <SHOPITEM><CODE>MK0813</CODE><CURRENCY>CZK</CURRENCY><PRICE>530557</PRICE><STANDARD_PRICE>551540</STANDARD_PRICE><FLAGS><FLAG><CODE>posledni-kus</CODE><ACTIVE>0</ACTIVE></FLAG><FLAG><CODE>trhem-overena-cena</CODE><ACTIVE>0</ACTIVE></FLAG></FLAGS> <STOCK><AMOUNT>5</AMOUNT></STOCK><INFORMATION_PARAMETERS><INFORMATION_PARAMETER><NAME>Výkupní cena</NAME><VALUE>493 625 Kč</VALUE></INFORMATION_PARAMETER></INFORMATION_PARAMETERS><HEUREKA_HIDDEN>1</HEUREKA_HIDDEN><ZBOZI_HIDDEN>1</ZBOZI_HIDDEN><AVAILABILITY_IN_STOCK>Dodání 5-10 dní</AVAILABILITY_IN_STOCK><FREE_SHIPPING>1</FREE_SHIPPING></SHOPITEM>
  <SHOPITEM><CODE>MK0812</CODE><CURRENCY>CZK</CURRENCY><PRICE>525748</PRICE><STANDARD_PRICE>534690</STANDARD_PRICE><FLAGS><FLAG><CODE>posledni-kus</CODE><ACTIVE>0</ACTIVE></FLAG><FLAG><CODE>trhem-overena-cena</CODE><ACTIVE>0</ACTIVE></FLAG></FLAGS> <STOCK><AMOUNT>8</AMOUNT></STOCK><INFORMATION_PARAMETERS><INFORMATION_PARAMETER><NAME>Výkupní cena</NAME><VALUE>490 644 Kč</VALUE></INFORMATION_PARAMETER></INFORMATION_PARAMETERS><HEUREKA_HIDDEN>1</HEUREKA_HIDDEN><ZBOZI_HIDDEN>1</ZBOZI_HIDDEN><AVAILABILITY_IN_STOCK>Dodání 5-10 dní</AVAILABILITY_IN_STOCK><FREE_SHIPPING>1</FREE_SHIPPING></SHOPITEM>
  <SHOPITEM><CODE>MK0816</CODE><CURRENCY>CZK</CURRENCY><PRICE>1020306</PRICE><STANDARD_PRICE>1024950</STANDARD_PRICE><FLAGS><FLAG><CODE>posledni-kus</CODE><ACTIVE>0</ACTIVE></FLAG><FLAG><CODE>trhem-overena-cena</CODE><ACTIVE>1</ACTIVE></FLAG></FLAGS> <STOCK><AMOUNT>16</AMOUNT></STOCK><INFORMATION_PARAMETERS><INFORMATION_PARAMETER><NAME>Výkupní cena</NAME><VALUE>985 964 Kč</VALUE></INFORMATION_PARAMETER></INFORMATION_PARAMETERS><HEUREKA_HIDDEN>0</HEUREKA_HIDDEN><ZBOZI_HIDDEN>0</ZBOZI_HIDDEN><AVAILABILITY_IN_STOCK>Dodání 5-10 dní</AVAILABILITY_IN_STOCK><FREE_SHIPPING>1</FREE_SHIPPING></SHOPITEM>
  <SHOPITEM><CODE>MK0826</CODE><CURRENCY>CZK</CURRENCY><PRICE>51029506</PRICE><STANDARD_PRICE>51247500</STANDARD_PRICE><FLAGS><FLAG><CODE>posledni-kus</CODE><ACTIVE>0</ACTIVE></FLAG><FLAG><CODE>trhem-overena-cena</CODE><ACTIVE>0</ACTIVE></FLAG></FLAGS> <STOCK><AMOUNT>5</AMOUNT></STOCK><INFORMATION_PARAMETERS><INFORMATION_PARAMETER><NAME>Výkupní cena</NAME><VALUE>49 763 211 Kč</VALUE></INFORMATION_PARAMETER></INFORMATION_PARAMETERS><HEUREKA_HIDDEN>1</HEUREKA_HIDDEN><ZBOZI_HIDDEN>1</ZBOZI_HIDDEN><AVAILABILITY_IN_STOCK>Dodání 5-10 dní</AVAILABILITY_IN_STOCK><FREE_SHIPPING>1</FREE_SHIPPING></SHOPITEM>
  <SHOPITEM><CODE>MK0556</CODE><CURRENCY>CZK</CURRENCY><PRICE>3541</PRICE><FLAGS><FLAG><CODE>posledni-kus</CODE><ACTIVE>0</ACTIVE></FLAG><FLAG><CODE>trhem-overena-cena</CODE><ACTIVE>0</ACTIVE></FLAG></FLAGS> <STOCK><AMOUNT>594</AMOUNT></STOCK><INFORMATION_PARAMETERS><INFORMATION_PARAMETER><NAME>Výkupní cena</NAME><VALUE>3 330 Kč</VALUE></INFORMATION_PARAMETER></INFORMATION_PARAMETERS><HEUREKA_HIDDEN>1</HEUREKA_HIDDEN><ZBOZI_HIDDEN>1</ZBOZI_HIDDEN><AVAILABILITY_IN_STOCK>Skladem</AVAILABILITY_IN_STOCK><FREE_SHIPPING>0</FREE_SHIPPING></SHOPITEM>
  <SHOPITEM><CODE>MK0557</CODE><CURRENCY>CZK</CURRENCY><PRICE>6852</PRICE><FLAGS><FLAG><CODE>posledni-kus</CODE><ACTIVE>0</ACTIVE></FLAG><FLAG><CODE>trhem-overena-cena</CODE><ACTIVE>0</ACTIVE></FLAG></FLAGS> <STOCK><AMOUNT>1014</AMOUNT></STOCK><INFORMATION_PARAMETERS><INFORMATION_PARAMETER><NAME>Výkupní cena</NAME><VALUE>6 558 Kč</VALUE></INFORMATION_PARAMETER></INFORMATION_PARAMETERS><HEUREKA_HIDDEN>1</HEUREKA_HIDDEN><ZBOZI_HIDDEN>1</ZBOZI_HIDDEN><AVAILABILITY_IN_STOCK>Skladem</AVAILABILITY_IN_STOCK><FREE_SHIPPING>0</FREE_SHIPPING></SHOPITEM>
  <SHOPITEM><CODE>MK0558</CODE><CURRENCY>CZK</CURRENCY><PRICE>16659</PRICE><FLAGS><FLAG><CODE>posledni-kus</CODE><ACTIVE>0</ACTIVE></FLAG><FLAG><CODE>trhem-overena-cena</CODE><ACTIVE>0</ACTIVE></FLAG></FLAGS> <STOCK><AMOUNT>1089</AMOUNT></STOCK><INFORMATION_PARAMETERS><INFORMATION_PARAMETER><NAME>Výkupní cena</NAME><VALUE>16 038 Kč</VALUE></INFORMATION_PARAMETER></INFORMATION_PARAMETERS><HEUREKA_HIDDEN>1</HEUREKA_HIDDEN><ZBOZI_HIDDEN>1</ZBOZI_HIDDEN><AVAILABILITY_IN_STOCK>Skladem</AVAILABILITY_IN_STOCK><FREE_SHIPPING>0</FREE_SHIPPING></SHOPITEM>
  <SHOPITEM><CODE>MK0559</CODE><CURRENCY>CZK</CURRENCY><PRICE>32943</PRICE><FLAGS><FLAG><CODE>posledni-kus</CODE><ACTIVE>0</ACTIVE></FLAG><FLAG><CODE>trhem-overena-cena</CODE><ACTIVE>0</ACTIVE></FLAG></FLAGS> <STOCK><AMOUNT>1296</AMOUNT></STOCK><INFORMATION_PARAMETERS><INFORMATION_PARAMETER><NAME>Výkupní cena</NAME><VALUE>32 038 Kč</VALUE></INFORMATION_PARAMETER></INFORMATION_PARAMETERS><HEUREKA_HIDDEN>1</HEUREKA_HIDDEN><ZBOZI_HIDDEN>1</ZBOZI_HIDDEN><AVAILABILITY_IN_STOCK>Skladem</AVAILABILITY_IN_STOCK><FREE_SHIPPING>0</FREE_SHIPPING></SHOPITEM>
  <SHOPITEM><CODE>MK0560</CODE><CURRENCY>CZK</CURRENCY><PRICE>65378</PRICE><FLAGS><FLAG><CODE>posledni-kus</CODE><ACTIVE>0</ACTIVE></FLAG><FLAG><CODE>trhem-overena-cena</CODE><ACTIVE>0</ACTIVE></FLAG></FLAGS> <STOCK><AMOUNT>33</AMOUNT></STOCK><INFORMATION_PARAMETERS><INFORMATION_PARAMETER><NAME>Výkupní cena</NAME><VALUE>63 873 Kč</VALUE></INFORMATION_PARAMETER></INFORMATION_PARAMETERS><HEUREKA_HIDDEN>1</HEUREKA_HIDDEN><ZBOZI_HIDDEN>1</ZBOZI_HIDDEN><AVAILABILITY_IN_STOCK>Skladem</AVAILABILITY_IN_STOCK><FREE_SHIPPING>1</FREE_SHIPPING></SHOPITEM>
  <SHOPITEM><CODE>MK0561</CODE><CURRENCY>CZK</CURRENCY><PRICE>101967</PRICE><FLAGS><FLAG><CODE>posledni-kus</CODE><ACTIVE>0</ACTIVE></FLAG><FLAG><CODE>trhem-overena-cena</CODE><ACTIVE>0</ACTIVE></FLAG></FLAGS> <STOCK><AMOUNT>5</AMOUNT></STOCK><INFORMATION_PARAMETERS><INFORMATION_PARAMETER><NAME>Výkupní cena</NAME><VALUE>99 565 Kč</VALUE></INFORMATION_PARAMETER></INFORMATION_PARAMETERS><HEUREKA_HIDDEN>1</HEUREKA_HIDDEN><ZBOZI_HIDDEN>1</ZBOZI_HIDDEN><AVAILABILITY_IN_STOCK>Skladem</AVAILABILITY_IN_STOCK><FREE_SHIPPING>1</FREE_SHIPPING></SHOPITEM>
  <SHOPITEM><CODE>MK0562</CODE><CURRENCY>CZK</CURRENCY><PRICE>164876</PRICE><FLAGS><FLAG><CODE>posledni-kus</CODE><ACTIVE>0</ACTIVE></FLAG><FLAG><CODE>trhem-overena-cena</CODE><ACTIVE>0</ACTIVE></FLAG></FLAGS> <STOCK><AMOUNT>5</AMOUNT></STOCK><INFORMATION_PARAMETERS><INFORMATION_PARAMETER><NAME>Výkupní cena</NAME><VALUE>160 621 Kč</VALUE></INFORMATION_PARAMETER></INFORMATION_PARAMETERS><HEUREKA_HIDDEN>1</HEUREKA_HIDDEN><ZBOZI_HIDDEN>1</ZBOZI_HIDDEN><AVAILABILITY_IN_STOCK>Skladem</AVAILABILITY_IN_STOCK><FREE_SHIPPING>1</FREE_SHIPPING></SHOPITEM>
  <SHOPITEM><CODE>MK0563</CODE><CURRENCY>CZK</CURRENCY><PRICE>332891</PRICE><FLAGS><FLAG><CODE>posledni-kus</CODE><ACTIVE>0</ACTIVE></FLAG><FLAG><CODE>trhem-overena-cena</CODE><ACTIVE>0</ACTIVE></FLAG></FLAGS> <STOCK><AMOUNT>5</AMOUNT></STOCK><INFORMATION_PARAMETERS><INFORMATION_PARAMETER><NAME>Výkupní cena</NAME><VALUE>306 741 Kč</VALUE></INFORMATION_PARAMETER></INFORMATION_PARAMETERS><HEUREKA_HIDDEN>1</HEUREKA_HIDDEN><ZBOZI_HIDDEN>1</ZBOZI_HIDDEN><AVAILABILITY_IN_STOCK>Dodání 5-10 dní</AVAILABILITY_IN_STOCK><FREE_SHIPPING>1</FREE_SHIPPING></SHOPITEM>
  <SHOPITEM><CODE>MK0767</CODE><CURRENCY>CZK</CURRENCY><PRICE>165999</PRICE><FLAGS><FLAG><CODE>posledni-kus</CODE><ACTIVE>0</ACTIVE></FLAG><FLAG><CODE>trhem-overena-cena</CODE><ACTIVE>0</ACTIVE></FLAG></FLAGS> <STOCK><AMOUNT>0</AMOUNT></STOCK><INFORMATION_PARAMETERS><INFORMATION_PARAMETER><NAME>Výkupní cena</NAME><VALUE>155 560 Kč</VALUE></INFORMATION_PARAMETER></INFORMATION_PARAMETERS><HEUREKA_HIDDEN>0</HEUREKA_HIDDEN><ZBOZI_HIDDEN>0</ZBOZI_HIDDEN><AVAILABILITY_IN_STOCK>Dodání 5-10 dní</AVAILABILITY_IN_STOCK><FREE_SHIPPING>0</FREE_SHIPPING></SHOPITEM>
  <SHOPITEM><CODE>MK0572</CODE><CURRENCY>CZK</CURRENCY><PRICE>330174</PRICE><FLAGS><FLAG><CODE>posledni-kus</CODE><ACTIVE>0</ACTIVE></FLAG><FLAG><CODE>trhem-overena-cena</CODE><ACTIVE>0</ACTIVE></FLAG></FLAGS> <STOCK><AMOUNT>5</AMOUNT></STOCK><INFORMATION_PARAMETERS><INFORMATION_PARAMETER><NAME>Výkupní cena</NAME><VALUE>314 236 Kč</VALUE></INFORMATION_PARAMETER></INFORMATION_PARAMETERS><HEUREKA_HIDDEN>1</HEUREKA_HIDDEN><ZBOZI_HIDDEN>1</ZBOZI_HIDDEN><AVAILABILITY_IN_STOCK>Dodání 5-10 dní</AVAILABILITY_IN_STOCK><FREE_SHIPPING>1</FREE_SHIPPING></SHOPITEM>
  <SHOPITEM><CODE>MK0573</CODE><CURRENCY>CZK</CURRENCY><PRICE>819662</PRICE><FLAGS><FLAG><CODE>posledni-kus</CODE><ACTIVE>0</ACTIVE></FLAG><FLAG><CODE>trhem-overena-cena</CODE><ACTIVE>0</ACTIVE></FLAG></FLAGS> <STOCK><AMOUNT>5</AMOUNT></STOCK><INFORMATION_PARAMETERS><INFORMATION_PARAMETER><NAME>Výkupní cena</NAME><VALUE>788 796 Kč</VALUE></INFORMATION_PARAMETER></INFORMATION_PARAMETERS><HEUREKA_HIDDEN>1</HEUREKA_HIDDEN><ZBOZI_HIDDEN>1</ZBOZI_HIDDEN><AVAILABILITY_IN_STOCK>Dodání 5-10 dní</AVAILABILITY_IN_STOCK><FREE_SHIPPING>1</FREE_SHIPPING></SHOPITEM>
  <SHOPITEM><CODE>MK0574</CODE><CURRENCY>CZK</CURRENCY><PRICE>1647127</PRICE><FLAGS><FLAG><CODE>posledni-kus</CODE><ACTIVE>0</ACTIVE></FLAG><FLAG><CODE>trhem-overena-cena</CODE><ACTIVE>0</ACTIVE></FLAG></FLAGS> <STOCK><AMOUNT>5</AMOUNT></STOCK><INFORMATION_PARAMETERS><INFORMATION_PARAMETER><NAME>Výkupní cena</NAME><VALUE>1 587 469 Kč</VALUE></INFORMATION_PARAMETER></INFORMATION_PARAMETERS><HEUREKA_HIDDEN>1</HEUREKA_HIDDEN><ZBOZI_HIDDEN>1</ZBOZI_HIDDEN><AVAILABILITY_IN_STOCK>Dodání 5-10 dní</AVAILABILITY_IN_STOCK><FREE_SHIPPING>1</FREE_SHIPPING></SHOPITEM>
  <SHOPITEM><CODE>MK0575</CODE><CURRENCY>CZK</CURRENCY><PRICE>3292033</PRICE><FLAGS><FLAG><CODE>posledni-kus</CODE><ACTIVE>0</ACTIVE></FLAG><FLAG><CODE>trhem-overena-cena</CODE><ACTIVE>0</ACTIVE></FLAG></FLAGS> <STOCK><AMOUNT>5</AMOUNT></STOCK><INFORMATION_PARAMETERS><INFORMATION_PARAMETER><NAME>Výkupní cena</NAME><VALUE>3 173 735 Kč</VALUE></INFORMATION_PARAMETER></INFORMATION_PARAMETERS><HEUREKA_HIDDEN>1</HEUREKA_HIDDEN><ZBOZI_HIDDEN>1</ZBOZI_HIDDEN><AVAILABILITY_IN_STOCK>Dodání 5-10 dní</AVAILABILITY_IN_STOCK><FREE_SHIPPING>1</FREE_SHIPPING></SHOPITEM>
  <SHOPITEM><CODE>MK0777</CODE><CURRENCY>CZK</CURRENCY><PRICE>3902</PRICE><FLAGS><FLAG><CODE>posledni-kus</CODE><ACTIVE>0</ACTIVE></FLAG><FLAG><CODE>trhem-overena-cena</CODE><ACTIVE>0</ACTIVE></FLAG></FLAGS> <STOCK><AMOUNT>5</AMOUNT></STOCK><INFORMATION_PARAMETERS><INFORMATION_PARAMETER><NAME>Výkupní cena</NAME><VALUE>3 445 Kč</VALUE></INFORMATION_PARAMETER></INFORMATION_PARAMETERS><HEUREKA_HIDDEN>1</HEUREKA_HIDDEN><ZBOZI_HIDDEN>1</ZBOZI_HIDDEN><AVAILABILITY_IN_STOCK>Dodání 5-10 dní</AVAILABILITY_IN_STOCK><FREE_SHIPPING>0</FREE_SHIPPING></SHOPITEM>
  <SHOPITEM><CODE>MK0776</CODE><CURRENCY>CZK</CURRENCY><PRICE>17868</PRICE><FLAGS><FLAG><CODE>posledni-kus</CODE><ACTIVE>0</ACTIVE></FLAG><FLAG><CODE>trhem-overena-cena</CODE><ACTIVE>0</ACTIVE></FLAG></FLAGS> <STOCK><AMOUNT>5</AMOUNT></STOCK><INFORMATION_PARAMETERS><INFORMATION_PARAMETER><NAME>Výkupní cena</NAME><VALUE>16 409 Kč</VALUE></INFORMATION_PARAMETER></INFORMATION_PARAMETERS><HEUREKA_HIDDEN>1</HEUREKA_HIDDEN><ZBOZI_HIDDEN>1</ZBOZI_HIDDEN><AVAILABILITY_IN_STOCK>Dodání do 15 dní</AVAILABILITY_IN_STOCK><FREE_SHIPPING>0</FREE_SHIPPING></SHOPITEM>
  <SHOPITEM><CODE>MK0775</CODE><CURRENCY>CZK</CURRENCY><PRICE>34758</PRICE><FLAGS><FLAG><CODE>posledni-kus</CODE><ACTIVE>0</ACTIVE></FLAG><FLAG><CODE>trhem-overena-cena</CODE><ACTIVE>0</ACTIVE></FLAG></FLAGS> <STOCK><AMOUNT>5</AMOUNT></STOCK><INFORMATION_PARAMETERS><INFORMATION_PARAMETER><NAME>Výkupní cena</NAME><VALUE>32 347 Kč</VALUE></INFORMATION_PARAMETER></INFORMATION_PARAMETERS><HEUREKA_HIDDEN>1</HEUREKA_HIDDEN><ZBOZI_HIDDEN>1</ZBOZI_HIDDEN><AVAILABILITY_IN_STOCK>Dodání 5-10 dní</AVAILABILITY_IN_STOCK><FREE_SHIPPING>0</FREE_SHIPPING></SHOPITEM>
  <SHOPITEM><CODE>MK0774</CODE><CURRENCY>CZK</CURRENCY><PRICE>103808</PRICE><FLAGS><FLAG><CODE>posledni-kus</CODE><ACTIVE>0</ACTIVE></FLAG><FLAG><CODE>trhem-overena-cena</CODE><ACTIVE>0</ACTIVE></FLAG></FLAGS> <STOCK><AMOUNT>5</AMOUNT></STOCK><INFORMATION_PARAMETERS><INFORMATION_PARAMETER><NAME>Výkupní cena</NAME><VALUE>99 335 Kč</VALUE></INFORMATION_PARAMETER></INFORMATION_PARAMETERS><HEUREKA_HIDDEN>1</HEUREKA_HIDDEN><ZBOZI_HIDDEN>1</ZBOZI_HIDDEN><AVAILABILITY_IN_STOCK>Skladem</AVAILABILITY_IN_STOCK><FREE_SHIPPING>1</FREE_SHIPPING></SHOPITEM>
  <SHOPITEM><CODE>MK0670</CODE><CURRENCY>CZK</CURRENCY><PRICE>111780</PRICE><FLAGS><FLAG><CODE>posledni-kus</CODE><ACTIVE>0</ACTIVE></FLAG><FLAG><CODE>trhem-overena-cena</CODE><ACTIVE>0</ACTIVE></FLAG></FLAGS> <STOCK><AMOUNT>5</AMOUNT></STOCK><INFORMATION_PARAMETERS><INFORMATION_PARAMETER><NAME>Výkupní cena</NAME><VALUE>96 592 Kč</VALUE></INFORMATION_PARAMETER></INFORMATION_PARAMETERS><HEUREKA_HIDDEN>1</HEUREKA_HIDDEN><ZBOZI_HIDDEN>1</ZBOZI_HIDDEN><AVAILABILITY_IN_STOCK>Dodání 5-10 dní</AVAILABILITY_IN_STOCK><FREE_SHIPPING>1</FREE_SHIPPING></SHOPITEM>
  <SHOPITEM><CODE>MK0671</CODE><CURRENCY>CZK</CURRENCY><PRICE>36373</PRICE><FLAGS><FLAG><CODE>posledni-kus</CODE><ACTIVE>0</ACTIVE></FLAG><FLAG><CODE>trhem-overena-cena</CODE><ACTIVE>0</ACTIVE></FLAG></FLAGS> <STOCK><AMOUNT>5</AMOUNT></STOCK><INFORMATION_PARAMETERS><INFORMATION_PARAMETER><NAME>Výkupní cena</NAME><VALUE>33 188 Kč</VALUE></INFORMATION_PARAMETER></INFORMATION_PARAMETERS><HEUREKA_HIDDEN>1</HEUREKA_HIDDEN><ZBOZI_HIDDEN>1</ZBOZI_HIDDEN><AVAILABILITY_IN_STOCK>Skladem</AVAILABILITY_IN_STOCK><FREE_SHIPPING>0</FREE_SHIPPING></SHOPITEM>
  <SHOPITEM><CODE>MK0861</CODE><CURRENCY>CZK</CURRENCY><PRICE>3712</PRICE><FLAGS><FLAG><CODE>posledni-kus</CODE><ACTIVE>0</ACTIVE></FLAG><FLAG><CODE>trhem-overena-cena</CODE><ACTIVE>0</ACTIVE></FLAG></FLAGS> <STOCK><AMOUNT>5</AMOUNT></STOCK><INFORMATION_PARAMETERS><INFORMATION_PARAMETER><NAME>Výkupní cena</NAME><VALUE>3 268 Kč</VALUE></INFORMATION_PARAMETER></INFORMATION_PARAMETERS><HEUREKA_HIDDEN>1</HEUREKA_HIDDEN><ZBOZI_HIDDEN>1</ZBOZI_HIDDEN><AVAILABILITY_IN_STOCK>Skladem</AVAILABILITY_IN_STOCK><FREE_SHIPPING>0</FREE_SHIPPING></SHOPITEM>
  <SHOPITEM><CODE>MK0679</CODE><CURRENCY>CZK</CURRENCY><PRICE>6999</PRICE><FLAGS><FLAG><CODE>posledni-kus</CODE><ACTIVE>0</ACTIVE></FLAG><FLAG><CODE>trhem-overena-cena</CODE><ACTIVE>0</ACTIVE></FLAG></FLAGS> <STOCK><AMOUNT>5</AMOUNT></STOCK><INFORMATION_PARAMETERS><INFORMATION_PARAMETER><NAME>Výkupní cena</NAME><VALUE>6 557 Kč</VALUE></INFORMATION_PARAMETER></INFORMATION_PARAMETERS><HEUREKA_HIDDEN>1</HEUREKA_HIDDEN><ZBOZI_HIDDEN>1</ZBOZI_HIDDEN><AVAILABILITY_IN_STOCK>Skladem</AVAILABILITY_IN_STOCK><FREE_SHIPPING>0</FREE_SHIPPING></SHOPITEM>
  <SHOPITEM><CODE>MK0863</CODE><CURRENCY>CZK</CURRENCY><PRICE>17030</PRICE><FLAGS><FLAG><CODE>posledni-kus</CODE><ACTIVE>0</ACTIVE></FLAG><FLAG><CODE>trhem-overena-cena</CODE><ACTIVE>0</ACTIVE></FLAG></FLAGS> <STOCK><AMOUNT>481</AMOUNT></STOCK><INFORMATION_PARAMETERS><INFORMATION_PARAMETER><NAME>Výkupní cena</NAME><VALUE>15 777 Kč</VALUE></INFORMATION_PARAMETER></INFORMATION_PARAMETERS><HEUREKA_HIDDEN>1</HEUREKA_HIDDEN><ZBOZI_HIDDEN>1</ZBOZI_HIDDEN><AVAILABILITY_IN_STOCK>Skladem</AVAILABILITY_IN_STOCK><FREE_SHIPPING>0</FREE_SHIPPING></SHOPITEM>
  <SHOPITEM><CODE>MK0862</CODE><CURRENCY>CZK</CURRENCY><PRICE>33704</PRICE><FLAGS><FLAG><CODE>posledni-kus</CODE><ACTIVE>0</ACTIVE></FLAG><FLAG><CODE>trhem-overena-cena</CODE><ACTIVE>0</ACTIVE></FLAG></FLAGS> <STOCK><AMOUNT>5</AMOUNT></STOCK><INFORMATION_PARAMETERS><INFORMATION_PARAMETER><NAME>Výkupní cena</NAME><VALUE>31 095 Kč</VALUE></INFORMATION_PARAMETER></INFORMATION_PARAMETERS><HEUREKA_HIDDEN>1</HEUREKA_HIDDEN><ZBOZI_HIDDEN>1</ZBOZI_HIDDEN><AVAILABILITY_IN_STOCK>Skladem</AVAILABILITY_IN_STOCK><FREE_SHIPPING>0</FREE_SHIPPING></SHOPITEM>
  <SHOPITEM><CODE>MK0676</CODE><CURRENCY>CZK</CURRENCY><PRICE>65837</PRICE><FLAGS><FLAG><CODE>posledni-kus</CODE><ACTIVE>0</ACTIVE></FLAG><FLAG><CODE>trhem-overena-cena</CODE><ACTIVE>0</ACTIVE></FLAG></FLAGS> <STOCK><AMOUNT>127</AMOUNT></STOCK><INFORMATION_PARAMETERS><INFORMATION_PARAMETER><NAME>Výkupní cena</NAME><VALUE>63 026 Kč</VALUE></INFORMATION_PARAMETER></INFORMATION_PARAMETERS><HEUREKA_HIDDEN>1</HEUREKA_HIDDEN><ZBOZI_HIDDEN>1</ZBOZI_HIDDEN><AVAILABILITY_IN_STOCK>Dodání 5-10 dní</AVAILABILITY_IN_STOCK><FREE_SHIPPING>1</FREE_SHIPPING></SHOPITEM>
  <SHOPITEM><CODE>MK0675</CODE><CURRENCY>CZK</CURRENCY><PRICE>162554</PRICE><FLAGS><FLAG><CODE>posledni-kus</CODE><ACTIVE>0</ACTIVE></FLAG><FLAG><CODE>trhem-overena-cena</CODE><ACTIVE>0</ACTIVE></FLAG></FLAGS> <STOCK><AMOUNT>58</AMOUNT></STOCK><INFORMATION_PARAMETERS><INFORMATION_PARAMETER><NAME>Výkupní cena</NAME><VALUE>156 507 Kč</VALUE></INFORMATION_PARAMETER></INFORMATION_PARAMETERS><HEUREKA_HIDDEN>1</HEUREKA_HIDDEN><ZBOZI_HIDDEN>1</ZBOZI_HIDDEN><AVAILABILITY_IN_STOCK>Dodání do 15 dní</AVAILABILITY_IN_STOCK><FREE_SHIPPING>1</FREE_SHIPPING></SHOPITEM>
  <SHOPITEM><CODE>MK0688</CODE><CURRENCY>CZK</CURRENCY><PRICE>324431</PRICE><FLAGS><FLAG><CODE>posledni-kus</CODE><ACTIVE>0</ACTIVE></FLAG><FLAG><CODE>trhem-overena-cena</CODE><ACTIVE>1</ACTIVE></FLAG></FLAGS> <STOCK><AMOUNT>62</AMOUNT></STOCK><INFORMATION_PARAMETERS><INFORMATION_PARAMETER><NAME>Výkupní cena</NAME><VALUE>313 010 Kč</VALUE></INFORMATION_PARAMETER></INFORMATION_PARAMETERS><HEUREKA_HIDDEN>0</HEUREKA_HIDDEN><ZBOZI_HIDDEN>0</ZBOZI_HIDDEN><AVAILABILITY_IN_STOCK>Dodání 5-10 dní</AVAILABILITY_IN_STOCK><FREE_SHIPPING>1</FREE_SHIPPING></SHOPITEM>
  <SHOPITEM><CODE>MK0674</CODE><CURRENCY>CZK</CURRENCY><PRICE>812995</PRICE><FLAGS><FLAG><CODE>posledni-kus</CODE><ACTIVE>0</ACTIVE></FLAG><FLAG><CODE>trhem-overena-cena</CODE><ACTIVE>1</ACTIVE></FLAG></FLAGS> <STOCK><AMOUNT>14</AMOUNT></STOCK><INFORMATION_PARAMETERS><INFORMATION_PARAMETER><NAME>Výkupní cena</NAME><VALUE>782 892 Kč</VALUE></INFORMATION_PARAMETER></INFORMATION_PARAMETERS><HEUREKA_HIDDEN>0</HEUREKA_HIDDEN><ZBOZI_HIDDEN>0</ZBOZI_HIDDEN><AVAILABILITY_IN_STOCK>Dodání 5-10 dní</AVAILABILITY_IN_STOCK><FREE_SHIPPING>1</FREE_SHIPPING></SHOPITEM>
  <SHOPITEM><CODE>MK0673</CODE><CURRENCY>CZK</CURRENCY><PRICE>1616142</PRICE><FLAGS><FLAG><CODE>posledni-kus</CODE><ACTIVE>0</ACTIVE></FLAG><FLAG><CODE>trhem-overena-cena</CODE><ACTIVE>1</ACTIVE></FLAG></FLAGS> <STOCK><AMOUNT>11</AMOUNT></STOCK><INFORMATION_PARAMETERS><INFORMATION_PARAMETER><NAME>Výkupní cena</NAME><VALUE>1 565 786 Kč</VALUE></INFORMATION_PARAMETER></INFORMATION_PARAMETERS><HEUREKA_HIDDEN>0</HEUREKA_HIDDEN><ZBOZI_HIDDEN>0</ZBOZI_HIDDEN><AVAILABILITY_IN_STOCK>Dodání 5-10 dní</AVAILABILITY_IN_STOCK><FREE_SHIPPING>1</FREE_SHIPPING></SHOPITEM>
  <SHOPITEM><CODE>MK0672</CODE><CURRENCY>CZK</CURRENCY><PRICE>3238422</PRICE><FLAGS><FLAG><CODE>posledni-kus</CODE><ACTIVE>0</ACTIVE></FLAG><FLAG><CODE>trhem-overena-cena</CODE><ACTIVE>1</ACTIVE></FLAG></FLAGS> <STOCK><AMOUNT>24</AMOUNT></STOCK><INFORMATION_PARAMETERS><INFORMATION_PARAMETER><NAME>Výkupní cena</NAME><VALUE>3 131 553 Kč</VALUE></INFORMATION_PARAMETER></INFORMATION_PARAMETERS><HEUREKA_HIDDEN>0</HEUREKA_HIDDEN><ZBOZI_HIDDEN>0</ZBOZI_HIDDEN><AVAILABILITY_IN_STOCK>Dodání 5-10 dní</AVAILABILITY_IN_STOCK><FREE_SHIPPING>1</FREE_SHIPPING></SHOPITEM>
  <SHOPITEM><CODE>MK0707</CODE><CURRENCY>CZK</CURRENCY><PRICE>3816</PRICE><FLAGS><FLAG><CODE>posledni-kus</CODE><ACTIVE>0</ACTIVE></FLAG><FLAG><CODE>trhem-overena-cena</CODE><ACTIVE>0</ACTIVE></FLAG></FLAGS> <STOCK><AMOUNT>5</AMOUNT></STOCK><INFORMATION_PARAMETERS><INFORMATION_PARAMETER><NAME>Výkupní cena</NAME><VALUE>3 505 Kč</VALUE></INFORMATION_PARAMETER></INFORMATION_PARAMETERS><HEUREKA_HIDDEN>1</HEUREKA_HIDDEN><ZBOZI_HIDDEN>1</ZBOZI_HIDDEN><AVAILABILITY_IN_STOCK>Dodání 5-10 dní</AVAILABILITY_IN_STOCK><FREE_SHIPPING>0</FREE_SHIPPING></SHOPITEM>
  <SHOPITEM><CODE>MK0708</CODE><CURRENCY>CZK</CURRENCY><PRICE>9168</PRICE><FLAGS><FLAG><CODE>posledni-kus</CODE><ACTIVE>0</ACTIVE></FLAG><FLAG><CODE>trhem-overena-cena</CODE><ACTIVE>0</ACTIVE></FLAG></FLAGS> <STOCK><AMOUNT>5</AMOUNT></STOCK><INFORMATION_PARAMETERS><INFORMATION_PARAMETER><NAME>Výkupní cena</NAME><VALUE>8 401 Kč</VALUE></INFORMATION_PARAMETER></INFORMATION_PARAMETERS><HEUREKA_HIDDEN>1</HEUREKA_HIDDEN><ZBOZI_HIDDEN>1</ZBOZI_HIDDEN><AVAILABILITY_IN_STOCK>Skladem</AVAILABILITY_IN_STOCK><FREE_SHIPPING>0</FREE_SHIPPING></SHOPITEM>
  <SHOPITEM><CODE>MK0683</CODE><CURRENCY>CZK</CURRENCY><PRICE>17327</PRICE><FLAGS><FLAG><CODE>posledni-kus</CODE><ACTIVE>0</ACTIVE></FLAG><FLAG><CODE>trhem-overena-cena</CODE><ACTIVE>0</ACTIVE></FLAG></FLAGS> <STOCK><AMOUNT>5</AMOUNT></STOCK><INFORMATION_PARAMETERS><INFORMATION_PARAMETER><NAME>Výkupní cena</NAME><VALUE>16 436 Kč</VALUE></INFORMATION_PARAMETER></INFORMATION_PARAMETERS><HEUREKA_HIDDEN>1</HEUREKA_HIDDEN><ZBOZI_HIDDEN>1</ZBOZI_HIDDEN><AVAILABILITY_IN_STOCK>Dodání 5-10 dní</AVAILABILITY_IN_STOCK><FREE_SHIPPING>0</FREE_SHIPPING></SHOPITEM>
  <SHOPITEM><CODE>MK0709</CODE><CURRENCY>CZK</CURRENCY><PRICE>34011</PRICE><FLAGS><FLAG><CODE>posledni-kus</CODE><ACTIVE>0</ACTIVE></FLAG><FLAG><CODE>trhem-overena-cena</CODE><ACTIVE>0</ACTIVE></FLAG></FLAGS> <STOCK><AMOUNT>5</AMOUNT></STOCK><INFORMATION_PARAMETERS><INFORMATION_PARAMETER><NAME>Výkupní cena</NAME><VALUE>32 093 Kč</VALUE></INFORMATION_PARAMETER></INFORMATION_PARAMETERS><HEUREKA_HIDDEN>1</HEUREKA_HIDDEN><ZBOZI_HIDDEN>1</ZBOZI_HIDDEN><AVAILABILITY_IN_STOCK>Skladem</AVAILABILITY_IN_STOCK><FREE_SHIPPING>0</FREE_SHIPPING></SHOPITEM>
  <SHOPITEM><CODE>MK0682</CODE><CURRENCY>CZK</CURRENCY><PRICE>66701</PRICE><FLAGS><FLAG><CODE>posledni-kus</CODE><ACTIVE>0</ACTIVE></FLAG><FLAG><CODE>trhem-overena-cena</CODE><ACTIVE>0</ACTIVE></FLAG></FLAGS> <STOCK><AMOUNT>5</AMOUNT></STOCK><INFORMATION_PARAMETERS><INFORMATION_PARAMETER><NAME>Výkupní cena</NAME><VALUE>63 737 Kč</VALUE></INFORMATION_PARAMETER></INFORMATION_PARAMETERS><HEUREKA_HIDDEN>1</HEUREKA_HIDDEN><ZBOZI_HIDDEN>1</ZBOZI_HIDDEN><AVAILABILITY_IN_STOCK>Dodání 5-10 dní</AVAILABILITY_IN_STOCK><FREE_SHIPPING>1</FREE_SHIPPING></SHOPITEM>
  <SHOPITEM><CODE>MK0715</CODE><CURRENCY>CZK</CURRENCY><PRICE>103131</PRICE><FLAGS><FLAG><CODE>posledni-kus</CODE><ACTIVE>0</ACTIVE></FLAG><FLAG><CODE>trhem-overena-cena</CODE><ACTIVE>0</ACTIVE></FLAG></FLAGS> <STOCK><AMOUNT>5</AMOUNT></STOCK><INFORMATION_PARAMETERS><INFORMATION_PARAMETER><NAME>Výkupní cena</NAME><VALUE>99 641 Kč</VALUE></INFORMATION_PARAMETER></INFORMATION_PARAMETERS><HEUREKA_HIDDEN>1</HEUREKA_HIDDEN><ZBOZI_HIDDEN>1</ZBOZI_HIDDEN><AVAILABILITY_IN_STOCK>Dodání 5-10 dní</AVAILABILITY_IN_STOCK><FREE_SHIPPING>1</FREE_SHIPPING></SHOPITEM>
  <SHOPITEM><CODE>MK0710</CODE><CURRENCY>CZK</CURRENCY><PRICE>164304</PRICE><FLAGS><FLAG><CODE>posledni-kus</CODE><ACTIVE>0</ACTIVE></FLAG><FLAG><CODE>trhem-overena-cena</CODE><ACTIVE>0</ACTIVE></FLAG></FLAGS> <STOCK><AMOUNT>5</AMOUNT></STOCK><INFORMATION_PARAMETERS><INFORMATION_PARAMETER><NAME>Výkupní cena</NAME><VALUE>159 967 Kč</VALUE></INFORMATION_PARAMETER></INFORMATION_PARAMETERS><HEUREKA_HIDDEN>1</HEUREKA_HIDDEN><ZBOZI_HIDDEN>1</ZBOZI_HIDDEN><AVAILABILITY_IN_STOCK>Dodání 5-10 dní</AVAILABILITY_IN_STOCK><FREE_SHIPPING>1</FREE_SHIPPING></SHOPITEM>
  <SHOPITEM><CODE>MK0711</CODE><CURRENCY>CZK</CURRENCY><PRICE>326947</PRICE><FLAGS><FLAG><CODE>posledni-kus</CODE><ACTIVE>0</ACTIVE></FLAG><FLAG><CODE>trhem-overena-cena</CODE><ACTIVE>0</ACTIVE></FLAG></FLAGS> <STOCK><AMOUNT>5</AMOUNT></STOCK><INFORMATION_PARAMETERS><INFORMATION_PARAMETER><NAME>Výkupní cena</NAME><VALUE>315 965 Kč</VALUE></INFORMATION_PARAMETER></INFORMATION_PARAMETERS><HEUREKA_HIDDEN>1</HEUREKA_HIDDEN><ZBOZI_HIDDEN>1</ZBOZI_HIDDEN><AVAILABILITY_IN_STOCK>Dodání 5-10 dní</AVAILABILITY_IN_STOCK><FREE_SHIPPING>1</FREE_SHIPPING></SHOPITEM>
  <SHOPITEM><CODE>MK0712</CODE><CURRENCY>CZK</CURRENCY><PRICE>826822</PRICE><FLAGS><FLAG><CODE>posledni-kus</CODE><ACTIVE>0</ACTIVE></FLAG><FLAG><CODE>trhem-overena-cena</CODE><ACTIVE>0</ACTIVE></FLAG></FLAGS> <STOCK><AMOUNT>0</AMOUNT></STOCK><INFORMATION_PARAMETERS><INFORMATION_PARAMETER><NAME>Výkupní cena</NAME><VALUE>779 100 Kč</VALUE></INFORMATION_PARAMETER></INFORMATION_PARAMETERS><HEUREKA_HIDDEN>0</HEUREKA_HIDDEN><ZBOZI_HIDDEN>0</ZBOZI_HIDDEN><AVAILABILITY_IN_STOCK>Dodání 5-10 dní</AVAILABILITY_IN_STOCK><FREE_SHIPPING>0</FREE_SHIPPING></SHOPITEM>
  <SHOPITEM><CODE>MK0713</CODE><CURRENCY>CZK</CURRENCY><PRICE>1653645</PRICE><FLAGS><FLAG><CODE>posledni-kus</CODE><ACTIVE>0</ACTIVE></FLAG><FLAG><CODE>trhem-overena-cena</CODE><ACTIVE>0</ACTIVE></FLAG></FLAGS> <STOCK><AMOUNT>0</AMOUNT></STOCK><INFORMATION_PARAMETERS><INFORMATION_PARAMETER><NAME>Výkupní cena</NAME><VALUE>1 560 560 Kč</VALUE></INFORMATION_PARAMETER></INFORMATION_PARAMETERS><HEUREKA_HIDDEN>0</HEUREKA_HIDDEN><ZBOZI_HIDDEN>0</ZBOZI_HIDDEN><AVAILABILITY_IN_STOCK>Dodání 5-10 dní</AVAILABILITY_IN_STOCK><FREE_SHIPPING>0</FREE_SHIPPING></SHOPITEM>
  <SHOPITEM><CODE>MK0714</CODE><CURRENCY>CZK</CURRENCY><PRICE>3428997</PRICE><FLAGS><FLAG><CODE>posledni-kus</CODE><ACTIVE>0</ACTIVE></FLAG><FLAG><CODE>trhem-overena-cena</CODE><ACTIVE>0</ACTIVE></FLAG></FLAGS> <STOCK><AMOUNT>5</AMOUNT></STOCK><INFORMATION_PARAMETERS><INFORMATION_PARAMETER><NAME>Výkupní cena</NAME><VALUE>3 105 698 Kč</VALUE></INFORMATION_PARAMETER></INFORMATION_PARAMETERS><HEUREKA_HIDDEN>1</HEUREKA_HIDDEN><ZBOZI_HIDDEN>1</ZBOZI_HIDDEN><AVAILABILITY_IN_STOCK>Dodání 5-10 dní</AVAILABILITY_IN_STOCK><FREE_SHIPPING>1</FREE_SHIPPING></SHOPITEM>
  <SHOPITEM><CODE>MK0684</CODE><CURRENCY>CZK</CURRENCY><PRICE>88619</PRICE><FLAGS><FLAG><CODE>posledni-kus</CODE><ACTIVE>0</ACTIVE></FLAG><FLAG><CODE>trhem-overena-cena</CODE><ACTIVE>0</ACTIVE></FLAG></FLAGS> <STOCK><AMOUNT>5</AMOUNT></STOCK><INFORMATION_PARAMETERS><INFORMATION_PARAMETER><NAME>Výkupní cena</NAME><VALUE>77 636 Kč</VALUE></INFORMATION_PARAMETER></INFORMATION_PARAMETERS><HEUREKA_HIDDEN>1</HEUREKA_HIDDEN><ZBOZI_HIDDEN>1</ZBOZI_HIDDEN><AVAILABILITY_IN_STOCK>Dodání 5-10 dní</AVAILABILITY_IN_STOCK><FREE_SHIPPING>1</FREE_SHIPPING></SHOPITEM>
  <SHOPITEM><CODE>MK0725</CODE><CURRENCY>CZK</CURRENCY><PRICE>5345</PRICE><FLAGS><FLAG><CODE>posledni-kus</CODE><ACTIVE>0</ACTIVE></FLAG><FLAG><CODE>trhem-overena-cena</CODE><ACTIVE>0</ACTIVE></FLAG></FLAGS> <STOCK><AMOUNT>0</AMOUNT></STOCK><INFORMATION_PARAMETERS><INFORMATION_PARAMETER><NAME>Výkupní cena</NAME><VALUE>4 911 Kč</VALUE></INFORMATION_PARAMETER></INFORMATION_PARAMETERS><HEUREKA_HIDDEN>0</HEUREKA_HIDDEN><ZBOZI_HIDDEN>0</ZBOZI_HIDDEN><AVAILABILITY_IN_STOCK>Dodání 5-10 dní</AVAILABILITY_IN_STOCK><FREE_SHIPPING>0</FREE_SHIPPING></SHOPITEM>
  <SHOPITEM><CODE>MK0724</CODE><CURRENCY>CZK</CURRENCY><PRICE>10751</PRICE><FLAGS><FLAG><CODE>posledni-kus</CODE><ACTIVE>0</ACTIVE></FLAG><FLAG><CODE>trhem-overena-cena</CODE><ACTIVE>0</ACTIVE></FLAG></FLAGS> <STOCK><AMOUNT>30</AMOUNT></STOCK><INFORMATION_PARAMETERS><INFORMATION_PARAMETER><NAME>Výkupní cena</NAME><VALUE>9 972 Kč</VALUE></INFORMATION_PARAMETER></INFORMATION_PARAMETERS><HEUREKA_HIDDEN>1</HEUREKA_HIDDEN><ZBOZI_HIDDEN>1</ZBOZI_HIDDEN><AVAILABILITY_IN_STOCK>Dodání 5-10 dní</AVAILABILITY_IN_STOCK><FREE_SHIPPING>0</FREE_SHIPPING></SHOPITEM>
  <SHOPITEM><CODE>MK0722</CODE><CURRENCY>CZK</CURRENCY><PRICE>27136</PRICE><FLAGS><FLAG><CODE>posledni-kus</CODE><ACTIVE>0</ACTIVE></FLAG><FLAG><CODE>trhem-overena-cena</CODE><ACTIVE>0</ACTIVE></FLAG></FLAGS> <STOCK><AMOUNT>5</AMOUNT></STOCK><INFORMATION_PARAMETERS><INFORMATION_PARAMETER><NAME>Výkupní cena</NAME><VALUE>25 809 Kč</VALUE></INFORMATION_PARAMETER></INFORMATION_PARAMETERS><HEUREKA_HIDDEN>1</HEUREKA_HIDDEN><ZBOZI_HIDDEN>1</ZBOZI_HIDDEN><AVAILABILITY_IN_STOCK>Dodání 5-10 dní</AVAILABILITY_IN_STOCK><FREE_SHIPPING>0</FREE_SHIPPING></SHOPITEM>
  <SHOPITEM><CODE>MK0745</CODE><CURRENCY>CZK</CURRENCY><PRICE>53505</PRICE><FLAGS><FLAG><CODE>posledni-kus</CODE><ACTIVE>0</ACTIVE></FLAG><FLAG><CODE>trhem-overena-cena</CODE><ACTIVE>0</ACTIVE></FLAG></FLAGS> <STOCK><AMOUNT>5</AMOUNT></STOCK><INFORMATION_PARAMETERS><INFORMATION_PARAMETER><NAME>Výkupní cena</NAME><VALUE>50 663 Kč</VALUE></INFORMATION_PARAMETER></INFORMATION_PARAMETERS><HEUREKA_HIDDEN>1</HEUREKA_HIDDEN><ZBOZI_HIDDEN>1</ZBOZI_HIDDEN><AVAILABILITY_IN_STOCK>Dodání do 30 dní</AVAILABILITY_IN_STOCK><FREE_SHIPPING>1</FREE_SHIPPING></SHOPITEM>
  <SHOPITEM><CODE>MK0719</CODE><CURRENCY>CZK</CURRENCY><PRICE>102114</PRICE><FLAGS><FLAG><CODE>posledni-kus</CODE><ACTIVE>0</ACTIVE></FLAG><FLAG><CODE>trhem-overena-cena</CODE><ACTIVE>0</ACTIVE></FLAG></FLAGS> <STOCK><AMOUNT>5</AMOUNT></STOCK><INFORMATION_PARAMETERS><INFORMATION_PARAMETER><NAME>Výkupní cena</NAME><VALUE>97 784 Kč</VALUE></INFORMATION_PARAMETER></INFORMATION_PARAMETERS><HEUREKA_HIDDEN>1</HEUREKA_HIDDEN><ZBOZI_HIDDEN>1</ZBOZI_HIDDEN><AVAILABILITY_IN_STOCK>Skladem</AVAILABILITY_IN_STOCK><FREE_SHIPPING>1</FREE_SHIPPING></SHOPITEM>
  <SHOPITEM><CODE>MK0782</CODE><CURRENCY>CZK</CURRENCY><PRICE>101836</PRICE><FLAGS><FLAG><CODE>posledni-kus</CODE><ACTIVE>0</ACTIVE></FLAG><FLAG><CODE>trhem-overena-cena</CODE><ACTIVE>1</ACTIVE></FLAG></FLAGS> <STOCK><AMOUNT>459</AMOUNT></STOCK><INFORMATION_PARAMETERS><INFORMATION_PARAMETER><NAME>Výkupní cena</NAME><VALUE>99 354 Kč</VALUE></INFORMATION_PARAMETER></INFORMATION_PARAMETERS><HEUREKA_HIDDEN>0</HEUREKA_HIDDEN><ZBOZI_HIDDEN>0</ZBOZI_HIDDEN><AVAILABILITY_IN_STOCK>Dodání 5-10 dní</AVAILABILITY_IN_STOCK><FREE_SHIPPING>1</FREE_SHIPPING></SHOPITEM>
  <SHOPITEM><CODE>MK0825</CODE><CURRENCY>CZK</CURRENCY><PRICE>1028567</PRICE><STANDARD_PRICE>1018360</STANDARD_PRICE><FLAGS><FLAG><CODE>posledni-kus</CODE><ACTIVE>0</ACTIVE></FLAG><FLAG><CODE>trhem-overena-cena</CODE><ACTIVE>0</ACTIVE></FLAG></FLAGS> <STOCK><AMOUNT>0</AMOUNT></STOCK><INFORMATION_PARAMETERS><INFORMATION_PARAMETER><NAME>Výkupní cena</NAME><VALUE>967 591 Kč</VALUE></INFORMATION_PARAMETER></INFORMATION_PARAMETERS><HEUREKA_HIDDEN>0</HEUREKA_HIDDEN><ZBOZI_HIDDEN>0</ZBOZI_HIDDEN><AVAILABILITY_IN_STOCK>Dodání 5-10 dní</AVAILABILITY_IN_STOCK><FREE_SHIPPING>0</FREE_SHIPPING></SHOPITEM>
  <SHOPITEM><CODE>MK0829</CODE><CURRENCY>CZK</CURRENCY><PRICE>51349405</PRICE><STANDARD_PRICE>50918000</STANDARD_PRICE><FLAGS><FLAG><CODE>posledni-kus</CODE><ACTIVE>0</ACTIVE></FLAG><FLAG><CODE>trhem-overena-cena</CODE><ACTIVE>0</ACTIVE></FLAG></FLAGS> <STOCK><AMOUNT>0</AMOUNT></STOCK><INFORMATION_PARAMETERS><INFORMATION_PARAMETER><NAME>Výkupní cena</NAME><VALUE>48 623 631 Kč</VALUE></INFORMATION_PARAMETER></INFORMATION_PARAMETERS><HEUREKA_HIDDEN>0</HEUREKA_HIDDEN><ZBOZI_HIDDEN>0</ZBOZI_HIDDEN><AVAILABILITY_IN_STOCK>Dodání 5-10 dní</AVAILABILITY_IN_STOCK><FREE_SHIPPING>0</FREE_SHIPPING></SHOPITEM>
  <SHOPITEM><CODE>MK0729</CODE><CURRENCY>CZK</CURRENCY><PRICE>11340</PRICE><FLAGS><FLAG><CODE>posledni-kus</CODE><ACTIVE>0</ACTIVE></FLAG><FLAG><CODE>trhem-overena-cena</CODE><ACTIVE>0</ACTIVE></FLAG></FLAGS> <STOCK><AMOUNT>5</AMOUNT></STOCK><INFORMATION_PARAMETERS><INFORMATION_PARAMETER><NAME>Výkupní cena</NAME><VALUE>9 568 Kč</VALUE></INFORMATION_PARAMETER></INFORMATION_PARAMETERS><HEUREKA_HIDDEN>1</HEUREKA_HIDDEN><ZBOZI_HIDDEN>1</ZBOZI_HIDDEN><AVAILABILITY_IN_STOCK>Skladem</AVAILABILITY_IN_STOCK><FREE_SHIPPING>0</FREE_SHIPPING></SHOPITEM>
  <SHOPITEM><CODE>MK0728</CODE><CURRENCY>CZK</CURRENCY><PRICE>29259</PRICE><FLAGS><FLAG><CODE>posledni-kus</CODE><ACTIVE>0</ACTIVE></FLAG><FLAG><CODE>trhem-overena-cena</CODE><ACTIVE>0</ACTIVE></FLAG></FLAGS> <STOCK><AMOUNT>5</AMOUNT></STOCK><INFORMATION_PARAMETERS><INFORMATION_PARAMETER><NAME>Výkupní cena</NAME><VALUE>23 775 Kč</VALUE></INFORMATION_PARAMETER></INFORMATION_PARAMETERS><HEUREKA_HIDDEN>1</HEUREKA_HIDDEN><ZBOZI_HIDDEN>1</ZBOZI_HIDDEN><AVAILABILITY_IN_STOCK>Dodání 5-10 dní</AVAILABILITY_IN_STOCK><FREE_SHIPPING>0</FREE_SHIPPING></SHOPITEM>
  <SHOPITEM><CODE>MK0727</CODE><CURRENCY>CZK</CURRENCY><PRICE>54126</PRICE><FLAGS><FLAG><CODE>posledni-kus</CODE><ACTIVE>0</ACTIVE></FLAG><FLAG><CODE>trhem-overena-cena</CODE><ACTIVE>0</ACTIVE></FLAG></FLAGS> <STOCK><AMOUNT>5</AMOUNT></STOCK><INFORMATION_PARAMETERS><INFORMATION_PARAMETER><NAME>Výkupní cena</NAME><VALUE>50 531 Kč</VALUE></INFORMATION_PARAMETER></INFORMATION_PARAMETERS><HEUREKA_HIDDEN>1</HEUREKA_HIDDEN><ZBOZI_HIDDEN>1</ZBOZI_HIDDEN><AVAILABILITY_IN_STOCK>Dodání 5-10 dní</AVAILABILITY_IN_STOCK><FREE_SHIPPING>1</FREE_SHIPPING></SHOPITEM>
  <SHOPITEM><CODE>MK0726</CODE><CURRENCY>CZK</CURRENCY><PRICE>104813</PRICE><FLAGS><FLAG><CODE>posledni-kus</CODE><ACTIVE>0</ACTIVE></FLAG><FLAG><CODE>trhem-overena-cena</CODE><ACTIVE>0</ACTIVE></FLAG></FLAGS> <STOCK><AMOUNT>5</AMOUNT></STOCK><INFORMATION_PARAMETERS><INFORMATION_PARAMETER><NAME>Výkupní cena</NAME><VALUE>92 942 Kč</VALUE></INFORMATION_PARAMETER></INFORMATION_PARAMETERS><HEUREKA_HIDDEN>1</HEUREKA_HIDDEN><ZBOZI_HIDDEN>1</ZBOZI_HIDDEN><AVAILABILITY_IN_STOCK>Dodání 5-10 dní</AVAILABILITY_IN_STOCK><FREE_SHIPPING>1</FREE_SHIPPING></SHOPITEM>
  <SHOPITEM><CODE>MK0781</CODE><CURRENCY>CZK</CURRENCY><PRICE>11329</PRICE><FLAGS><FLAG><CODE>posledni-kus</CODE><ACTIVE>0</ACTIVE></FLAG><FLAG><CODE>trhem-overena-cena</CODE><ACTIVE>0</ACTIVE></FLAG></FLAGS> <STOCK><AMOUNT>5</AMOUNT></STOCK><INFORMATION_PARAMETERS><INFORMATION_PARAMETER><NAME>Výkupní cena</NAME><VALUE>10 336 Kč</VALUE></INFORMATION_PARAMETER></INFORMATION_PARAMETERS><HEUREKA_HIDDEN>1</HEUREKA_HIDDEN><ZBOZI_HIDDEN>1</ZBOZI_HIDDEN><AVAILABILITY_IN_STOCK>Dodání 5-10 dní</AVAILABILITY_IN_STOCK><FREE_SHIPPING>0</FREE_SHIPPING></SHOPITEM>
  <SHOPITEM><CODE>MK0779</CODE><CURRENCY>CZK</CURRENCY><PRICE>28420</PRICE><FLAGS><FLAG><CODE>posledni-kus</CODE><ACTIVE>0</ACTIVE></FLAG><FLAG><CODE>trhem-overena-cena</CODE><ACTIVE>0</ACTIVE></FLAG></FLAGS> <STOCK><AMOUNT>5</AMOUNT></STOCK><INFORMATION_PARAMETERS><INFORMATION_PARAMETER><NAME>Výkupní cena</NAME><VALUE>26 126 Kč</VALUE></INFORMATION_PARAMETER></INFORMATION_PARAMETERS><HEUREKA_HIDDEN>1</HEUREKA_HIDDEN><ZBOZI_HIDDEN>1</ZBOZI_HIDDEN><AVAILABILITY_IN_STOCK>Skladem</AVAILABILITY_IN_STOCK><FREE_SHIPPING>0</FREE_SHIPPING></SHOPITEM>
  <SHOPITEM><CODE>MK0780</CODE><CURRENCY>CZK</CURRENCY><PRICE>54256</PRICE><FLAGS><FLAG><CODE>posledni-kus</CODE><ACTIVE>0</ACTIVE></FLAG><FLAG><CODE>trhem-overena-cena</CODE><ACTIVE>0</ACTIVE></FLAG></FLAGS> <STOCK><AMOUNT>5</AMOUNT></STOCK><INFORMATION_PARAMETERS><INFORMATION_PARAMETER><NAME>Výkupní cena</NAME><VALUE>50 714 Kč</VALUE></INFORMATION_PARAMETER></INFORMATION_PARAMETERS><HEUREKA_HIDDEN>1</HEUREKA_HIDDEN><ZBOZI_HIDDEN>1</ZBOZI_HIDDEN><AVAILABILITY_IN_STOCK>Dodání 5-10 dní</AVAILABILITY_IN_STOCK><FREE_SHIPPING>1</FREE_SHIPPING></SHOPITEM>
  <SHOPITEM><CODE>MK0746</CODE><CURRENCY>CZK</CURRENCY><PRICE>105014</PRICE><FLAGS><FLAG><CODE>posledni-kus</CODE><ACTIVE>0</ACTIVE></FLAG><FLAG><CODE>trhem-overena-cena</CODE><ACTIVE>0</ACTIVE></FLAG></FLAGS> <STOCK><AMOUNT>5</AMOUNT></STOCK><INFORMATION_PARAMETERS><INFORMATION_PARAMETER><NAME>Výkupní cena</NAME><VALUE>99 883 Kč</VALUE></INFORMATION_PARAMETER></INFORMATION_PARAMETERS><HEUREKA_HIDDEN>1</HEUREKA_HIDDEN><ZBOZI_HIDDEN>1</ZBOZI_HIDDEN><AVAILABILITY_IN_STOCK>Dodání 5-10 dní</AVAILABILITY_IN_STOCK><FREE_SHIPPING>1</FREE_SHIPPING></SHOPITEM>
  <SHOPITEM><CODE>MK0820</CODE><CURRENCY>CZK</CURRENCY><PRICE>257635</PRICE><STANDARD_PRICE>283525</STANDARD_PRICE><FLAGS><FLAG><CODE>posledni-kus</CODE><ACTIVE>0</ACTIVE></FLAG><FLAG><CODE>trhem-overena-cena</CODE><ACTIVE>0</ACTIVE></FLAG></FLAGS> <STOCK><AMOUNT>0</AMOUNT></STOCK><INFORMATION_PARAMETERS><INFORMATION_PARAMETER><NAME>Výkupní cena</NAME><VALUE>245 784 Kč</VALUE></INFORMATION_PARAMETER></INFORMATION_PARAMETERS><HEUREKA_HIDDEN>0</HEUREKA_HIDDEN><ZBOZI_HIDDEN>0</ZBOZI_HIDDEN><AVAILABILITY_IN_STOCK>Dodání 5-10 dní</AVAILABILITY_IN_STOCK><FREE_SHIPPING>0</FREE_SHIPPING></SHOPITEM>
  <SHOPITEM><CODE>MK0819</CODE><CURRENCY>CZK</CURRENCY><PRICE>643576</PRICE><STANDARD_PRICE>691300</STANDARD_PRICE><FLAGS><FLAG><CODE>posledni-kus</CODE><ACTIVE>0</ACTIVE></FLAG><FLAG><CODE>trhem-overena-cena</CODE><ACTIVE>0</ACTIVE></FLAG></FLAGS> <STOCK><AMOUNT>0</AMOUNT></STOCK><INFORMATION_PARAMETERS><INFORMATION_PARAMETER><NAME>Výkupní cena</NAME><VALUE>602 915 Kč</VALUE></INFORMATION_PARAMETER></INFORMATION_PARAMETERS><HEUREKA_HIDDEN>0</HEUREKA_HIDDEN><ZBOZI_HIDDEN>0</ZBOZI_HIDDEN><AVAILABILITY_IN_STOCK>Dodání 5-10 dní</AVAILABILITY_IN_STOCK><FREE_SHIPPING>0</FREE_SHIPPING></SHOPITEM>
  <SHOPITEM><CODE>MK0818</CODE><CURRENCY>CZK</CURRENCY><PRICE>514530</PRICE><STANDARD_PRICE>535320</STANDARD_PRICE><FLAGS><FLAG><CODE>posledni-kus</CODE><ACTIVE>0</ACTIVE></FLAG><FLAG><CODE>trhem-overena-cena</CODE><ACTIVE>0</ACTIVE></FLAG></FLAGS> <STOCK><AMOUNT>0</AMOUNT></STOCK><INFORMATION_PARAMETERS><INFORMATION_PARAMETER><NAME>Výkupní cena</NAME><VALUE>482 089 Kč</VALUE></INFORMATION_PARAMETER></INFORMATION_PARAMETERS><HEUREKA_HIDDEN>0</HEUREKA_HIDDEN><ZBOZI_HIDDEN>0</ZBOZI_HIDDEN><AVAILABILITY_IN_STOCK>Dodání 5-10 dní</AVAILABILITY_IN_STOCK><FREE_SHIPPING>0</FREE_SHIPPING></SHOPITEM>
  <SHOPITEM><CODE>MK0817</CODE><CURRENCY>CZK</CURRENCY><PRICE>1028567</PRICE><STANDARD_PRICE>1051300</STANDARD_PRICE><FLAGS><FLAG><CODE>posledni-kus</CODE><ACTIVE>0</ACTIVE></FLAG><FLAG><CODE>trhem-overena-cena</CODE><ACTIVE>0</ACTIVE></FLAG></FLAGS> <STOCK><AMOUNT>0</AMOUNT></STOCK><INFORMATION_PARAMETERS><INFORMATION_PARAMETER><NAME>Výkupní cena</NAME><VALUE>965 152 Kč</VALUE></INFORMATION_PARAMETER></INFORMATION_PARAMETERS><HEUREKA_HIDDEN>0</HEUREKA_HIDDEN><ZBOZI_HIDDEN>0</ZBOZI_HIDDEN><AVAILABILITY_IN_STOCK>Dodání 5-10 dní</AVAILABILITY_IN_STOCK><FREE_SHIPPING>0</FREE_SHIPPING></SHOPITEM>
  <SHOPITEM><CODE>MK0828</CODE><CURRENCY>CZK</CURRENCY><PRICE>51349405</PRICE><STANDARD_PRICE>52565000</STANDARD_PRICE><FLAGS><FLAG><CODE>posledni-kus</CODE><ACTIVE>0</ACTIVE></FLAG><FLAG><CODE>trhem-overena-cena</CODE><ACTIVE>0</ACTIVE></FLAG></FLAGS> <STOCK><AMOUNT>0</AMOUNT></STOCK><INFORMATION_PARAMETERS><INFORMATION_PARAMETER><NAME>Výkupní cena</NAME><VALUE>48 501 059 Kč</VALUE></INFORMATION_PARAMETER></INFORMATION_PARAMETERS><HEUREKA_HIDDEN>0</HEUREKA_HIDDEN><ZBOZI_HIDDEN>0</ZBOZI_HIDDEN><AVAILABILITY_IN_STOCK>Dodání 5-10 dní</AVAILABILITY_IN_STOCK><FREE_SHIPPING>0</FREE_SHIPPING></SHOPITEM>
  <SHOPITEM><CODE>MK0703</CODE><CURRENCY>CZK</CURRENCY><PRICE>4091</PRICE><FLAGS><FLAG><CODE>posledni-kus</CODE><ACTIVE>0</ACTIVE></FLAG><FLAG><CODE>trhem-overena-cena</CODE><ACTIVE>0</ACTIVE></FLAG></FLAGS> <STOCK><AMOUNT>5</AMOUNT></STOCK><INFORMATION_PARAMETERS><INFORMATION_PARAMETER><NAME>Výkupní cena</NAME><VALUE>3 294 Kč</VALUE></INFORMATION_PARAMETER></INFORMATION_PARAMETERS><HEUREKA_HIDDEN>1</HEUREKA_HIDDEN><ZBOZI_HIDDEN>1</ZBOZI_HIDDEN><AVAILABILITY_IN_STOCK>Dodání 5-10 dní</AVAILABILITY_IN_STOCK><FREE_SHIPPING>0</FREE_SHIPPING></SHOPITEM>
  <SHOPITEM><CODE>MK0704</CODE><CURRENCY>CZK</CURRENCY><PRICE>18047</PRICE><FLAGS><FLAG><CODE>posledni-kus</CODE><ACTIVE>0</ACTIVE></FLAG><FLAG><CODE>trhem-overena-cena</CODE><ACTIVE>0</ACTIVE></FLAG></FLAGS> <STOCK><AMOUNT>5</AMOUNT></STOCK><INFORMATION_PARAMETERS><INFORMATION_PARAMETER><NAME>Výkupní cena</NAME><VALUE>16 052 Kč</VALUE></INFORMATION_PARAMETER></INFORMATION_PARAMETERS><HEUREKA_HIDDEN>1</HEUREKA_HIDDEN><ZBOZI_HIDDEN>1</ZBOZI_HIDDEN><AVAILABILITY_IN_STOCK>Dodání 5-10 dní</AVAILABILITY_IN_STOCK><FREE_SHIPPING>0</FREE_SHIPPING></SHOPITEM>
  <SHOPITEM><CODE>MK0733</CODE><CURRENCY>CZK</CURRENCY><PRICE>12886</PRICE><FLAGS><FLAG><CODE>posledni-kus</CODE><ACTIVE>0</ACTIVE></FLAG><FLAG><CODE>trhem-overena-cena</CODE><ACTIVE>0</ACTIVE></FLAG></FLAGS> <STOCK><AMOUNT>5</AMOUNT></STOCK><INFORMATION_PARAMETERS><INFORMATION_PARAMETER><NAME>Výkupní cena</NAME><VALUE>11 803 Kč</VALUE></INFORMATION_PARAMETER></INFORMATION_PARAMETERS><HEUREKA_HIDDEN>1</HEUREKA_HIDDEN><ZBOZI_HIDDEN>1</ZBOZI_HIDDEN><AVAILABILITY_IN_STOCK>Dodání 5-10 dní</AVAILABILITY_IN_STOCK><FREE_SHIPPING>0</FREE_SHIPPING></SHOPITEM>
  <SHOPITEM><CODE>MK0732</CODE><CURRENCY>CZK</CURRENCY><PRICE>30432</PRICE><FLAGS><FLAG><CODE>posledni-kus</CODE><ACTIVE>0</ACTIVE></FLAG><FLAG><CODE>trhem-overena-cena</CODE><ACTIVE>0</ACTIVE></FLAG></FLAGS> <STOCK><AMOUNT>5</AMOUNT></STOCK><INFORMATION_PARAMETERS><INFORMATION_PARAMETER><NAME>Výkupní cena</NAME><VALUE>23 790 Kč</VALUE></INFORMATION_PARAMETER></INFORMATION_PARAMETERS><HEUREKA_HIDDEN>1</HEUREKA_HIDDEN><ZBOZI_HIDDEN>1</ZBOZI_HIDDEN><AVAILABILITY_IN_STOCK>Dodání 5-10 dní</AVAILABILITY_IN_STOCK><FREE_SHIPPING>0</FREE_SHIPPING></SHOPITEM>
  <SHOPITEM><CODE>MK0731</CODE><CURRENCY>CZK</CURRENCY><PRICE>54182</PRICE><FLAGS><FLAG><CODE>posledni-kus</CODE><ACTIVE>0</ACTIVE></FLAG><FLAG><CODE>trhem-overena-cena</CODE><ACTIVE>0</ACTIVE></FLAG></FLAGS> <STOCK><AMOUNT>5</AMOUNT></STOCK><INFORMATION_PARAMETERS><INFORMATION_PARAMETER><NAME>Výkupní cena</NAME><VALUE>49 675 Kč</VALUE></INFORMATION_PARAMETER></INFORMATION_PARAMETERS><HEUREKA_HIDDEN>1</HEUREKA_HIDDEN><ZBOZI_HIDDEN>1</ZBOZI_HIDDEN><AVAILABILITY_IN_STOCK>Skladem</AVAILABILITY_IN_STOCK><FREE_SHIPPING>1</FREE_SHIPPING></SHOPITEM>
  <SHOPITEM><CODE>MK0730</CODE><CURRENCY>CZK</CURRENCY><PRICE>102669</PRICE><FLAGS><FLAG><CODE>posledni-kus</CODE><ACTIVE>0</ACTIVE></FLAG><FLAG><CODE>trhem-overena-cena</CODE><ACTIVE>1</ACTIVE></FLAG></FLAGS> <STOCK><AMOUNT>13</AMOUNT></STOCK><INFORMATION_PARAMETERS><INFORMATION_PARAMETER><NAME>Výkupní cena</NAME><VALUE>99 211 Kč</VALUE></INFORMATION_PARAMETER></INFORMATION_PARAMETERS><HEUREKA_HIDDEN>0</HEUREKA_HIDDEN><ZBOZI_HIDDEN>0</ZBOZI_HIDDEN><AVAILABILITY_IN_STOCK>Dodání 5-10 dní</AVAILABILITY_IN_STOCK><FREE_SHIPPING>1</FREE_SHIPPING></SHOPITEM>
  <SHOPITEM><CODE>MK0824</CODE><CURRENCY>CZK</CURRENCY><PRICE>411624</PRICE><STANDARD_PRICE>515440</STANDARD_PRICE><FLAGS><FLAG><CODE>posledni-kus</CODE><ACTIVE>0</ACTIVE></FLAG><FLAG><CODE>trhem-overena-cena</CODE><ACTIVE>0</ACTIVE></FLAG></FLAGS> <STOCK><AMOUNT>0</AMOUNT></STOCK><INFORMATION_PARAMETERS><INFORMATION_PARAMETER><NAME>Výkupní cena</NAME><VALUE>405 147 Kč</VALUE></INFORMATION_PARAMETER></INFORMATION_PARAMETERS><HEUREKA_HIDDEN>0</HEUREKA_HIDDEN><ZBOZI_HIDDEN>0</ZBOZI_HIDDEN><AVAILABILITY_IN_STOCK>Dodání 5-10 dní</AVAILABILITY_IN_STOCK><FREE_SHIPPING>0</FREE_SHIPPING></SHOPITEM>
  <SHOPITEM><CODE>MK0823</CODE><CURRENCY>CZK</CURRENCY><PRICE>1029228</PRICE><STANDARD_PRICE>1217280</STANDARD_PRICE><FLAGS><FLAG><CODE>posledni-kus</CODE><ACTIVE>0</ACTIVE></FLAG><FLAG><CODE>trhem-overena-cena</CODE><ACTIVE>0</ACTIVE></FLAG></FLAGS> <STOCK><AMOUNT>0</AMOUNT></STOCK><INFORMATION_PARAMETERS><INFORMATION_PARAMETER><NAME>Výkupní cena</NAME><VALUE>994 402 Kč</VALUE></INFORMATION_PARAMETER></INFORMATION_PARAMETERS><HEUREKA_HIDDEN>0</HEUREKA_HIDDEN><ZBOZI_HIDDEN>0</ZBOZI_HIDDEN><AVAILABILITY_IN_STOCK>Dodání 5-10 dní</AVAILABILITY_IN_STOCK><FREE_SHIPPING>0</FREE_SHIPPING></SHOPITEM>
  <SHOPITEM><CODE>MK0822</CODE><CURRENCY>CZK</CURRENCY><PRICE>2057133</PRICE><STANDARD_PRICE>2167280</STANDARD_PRICE><FLAGS><FLAG><CODE>posledni-kus</CODE><ACTIVE>0</ACTIVE></FLAG><FLAG><CODE>trhem-overena-cena</CODE><ACTIVE>0</ACTIVE></FLAG></FLAGS> <STOCK><AMOUNT>0</AMOUNT></STOCK><INFORMATION_PARAMETERS><INFORMATION_PARAMETER><NAME>Výkupní cena</NAME><VALUE>1 952 748 Kč</VALUE></INFORMATION_PARAMETER></INFORMATION_PARAMETERS><HEUREKA_HIDDEN>0</HEUREKA_HIDDEN><ZBOZI_HIDDEN>0</ZBOZI_HIDDEN><AVAILABILITY_IN_STOCK>Dodání 5-10 dní</AVAILABILITY_IN_STOCK><FREE_SHIPPING>0</FREE_SHIPPING></SHOPITEM>
  <SHOPITEM><CODE>MK0821</CODE><CURRENCY>CZK</CURRENCY><PRICE>2057133</PRICE><STANDARD_PRICE>2053380</STANDARD_PRICE><FLAGS><FLAG><CODE>posledni-kus</CODE><ACTIVE>0</ACTIVE></FLAG><FLAG><CODE>trhem-overena-cena</CODE><ACTIVE>0</ACTIVE></FLAG></FLAGS> <STOCK><AMOUNT>0</AMOUNT></STOCK><INFORMATION_PARAMETERS><INFORMATION_PARAMETER><NAME>Výkupní cena</NAME><VALUE>1 938 111 Kč</VALUE></INFORMATION_PARAMETER></INFORMATION_PARAMETERS><HEUREKA_HIDDEN>0</HEUREKA_HIDDEN><ZBOZI_HIDDEN>0</ZBOZI_HIDDEN><AVAILABILITY_IN_STOCK>Dodání 5-10 dní</AVAILABILITY_IN_STOCK><FREE_SHIPPING>0</FREE_SHIPPING></SHOPITEM>
  <SHOPITEM><CODE>MK0827</CODE><CURRENCY>CZK</CURRENCY><PRICE>51349405</PRICE><STANDARD_PRICE>51334500</STANDARD_PRICE><FLAGS><FLAG><CODE>posledni-kus</CODE><ACTIVE>0</ACTIVE></FLAG><FLAG><CODE>trhem-overena-cena</CODE><ACTIVE>0</ACTIVE></FLAG></FLAGS> <STOCK><AMOUNT>0</AMOUNT></STOCK><INFORMATION_PARAMETERS><INFORMATION_PARAMETER><NAME>Výkupní cena</NAME><VALUE>48 623 631 Kč</VALUE></INFORMATION_PARAMETER></INFORMATION_PARAMETERS><HEUREKA_HIDDEN>0</HEUREKA_HIDDEN><ZBOZI_HIDDEN>0</ZBOZI_HIDDEN><AVAILABILITY_IN_STOCK>Dodání 5-10 dní</AVAILABILITY_IN_STOCK><FREE_SHIPPING>0</FREE_SHIPPING></SHOPITEM>
  <SHOPITEM><CODE>MK0783</CODE><CURRENCY>CZK</CURRENCY><PRICE>101998</PRICE><FLAGS><FLAG><CODE>posledni-kus</CODE><ACTIVE>0</ACTIVE></FLAG><FLAG><CODE>trhem-overena-cena</CODE><ACTIVE>0</ACTIVE></FLAG></FLAGS> <STOCK><AMOUNT>49</AMOUNT></STOCK><INFORMATION_PARAMETERS><INFORMATION_PARAMETER><NAME>Výkupní cena</NAME><VALUE>99 052 Kč</VALUE></INFORMATION_PARAMETER></INFORMATION_PARAMETERS><HEUREKA_HIDDEN>1</HEUREKA_HIDDEN><ZBOZI_HIDDEN>1</ZBOZI_HIDDEN><AVAILABILITY_IN_STOCK>Dodání do 15 dní</AVAILABILITY_IN_STOCK><FREE_SHIPPING>1</FREE_SHIPPING></SHOPITEM>
  <SHOPITEM><CODE>MK0784</CODE><CURRENCY>CZK</CURRENCY><PRICE>54980</PRICE><FLAGS><FLAG><CODE>posledni-kus</CODE><ACTIVE>0</ACTIVE></FLAG><FLAG><CODE>trhem-overena-cena</CODE><ACTIVE>0</ACTIVE></FLAG></FLAGS> <STOCK><AMOUNT>5</AMOUNT></STOCK><INFORMATION_PARAMETERS><INFORMATION_PARAMETER><NAME>Výkupní cena</NAME><VALUE>51 101 Kč</VALUE></INFORMATION_PARAMETER></INFORMATION_PARAMETERS><HEUREKA_HIDDEN>1</HEUREKA_HIDDEN><ZBOZI_HIDDEN>1</ZBOZI_HIDDEN><AVAILABILITY_IN_STOCK>Dodání 5-10 dní</AVAILABILITY_IN_STOCK><FREE_SHIPPING>1</FREE_SHIPPING></SHOPITEM>
  <SHOPITEM><CODE>MK0785</CODE><CURRENCY>CZK</CURRENCY><PRICE>28329</PRICE><FLAGS><FLAG><CODE>posledni-kus</CODE><ACTIVE>0</ACTIVE></FLAG><FLAG><CODE>trhem-overena-cena</CODE><ACTIVE>0</ACTIVE></FLAG></FLAGS> <STOCK><AMOUNT>5</AMOUNT></STOCK><INFORMATION_PARAMETERS><INFORMATION_PARAMETER><NAME>Výkupní cena</NAME><VALUE>26 144 Kč</VALUE></INFORMATION_PARAMETER></INFORMATION_PARAMETERS><HEUREKA_HIDDEN>1</HEUREKA_HIDDEN><ZBOZI_HIDDEN>1</ZBOZI_HIDDEN><AVAILABILITY_IN_STOCK>Dodání 5-10 dní</AVAILABILITY_IN_STOCK><FREE_SHIPPING>0</FREE_SHIPPING></SHOPITEM>
  <SHOPITEM><CODE>MK0786</CODE><CURRENCY>CZK</CURRENCY><PRICE>11359</PRICE><FLAGS><FLAG><CODE>posledni-kus</CODE><ACTIVE>0</ACTIVE></FLAG><FLAG><CODE>trhem-overena-cena</CODE><ACTIVE>0</ACTIVE></FLAG></FLAGS> <STOCK><AMOUNT>5</AMOUNT></STOCK><INFORMATION_PARAMETERS><INFORMATION_PARAMETER><NAME>Výkupní cena</NAME><VALUE>10 783 Kč</VALUE></INFORMATION_PARAMETER></INFORMATION_PARAMETERS><HEUREKA_HIDDEN>1</HEUREKA_HIDDEN><ZBOZI_HIDDEN>1</ZBOZI_HIDDEN><AVAILABILITY_IN_STOCK>Skladem</AVAILABILITY_IN_STOCK><FREE_SHIPPING>0</FREE_SHIPPING></SHOPITEM>
  <SHOPITEM><CODE>MK0787</CODE><CURRENCY>CZK</CURRENCY><PRICE>101140</PRICE><FLAGS><FLAG><CODE>posledni-kus</CODE><ACTIVE>0</ACTIVE></FLAG><FLAG><CODE>trhem-overena-cena</CODE><ACTIVE>0</ACTIVE></FLAG></FLAGS> <STOCK><AMOUNT>7</AMOUNT></STOCK><INFORMATION_PARAMETERS><INFORMATION_PARAMETER><NAME>Výkupní cena</NAME><VALUE>98 997 Kč</VALUE></INFORMATION_PARAMETER></INFORMATION_PARAMETERS><HEUREKA_HIDDEN>1</HEUREKA_HIDDEN><ZBOZI_HIDDEN>1</ZBOZI_HIDDEN><AVAILABILITY_IN_STOCK>Skladem</AVAILABILITY_IN_STOCK><FREE_SHIPPING>1</FREE_SHIPPING></SHOPITEM>
  <SHOPITEM><CODE>MK0788</CODE><CURRENCY>CZK</CURRENCY><PRICE>52350</PRICE><FLAGS><FLAG><CODE>posledni-kus</CODE><ACTIVE>1</ACTIVE></FLAG><FLAG><CODE>trhem-overena-cena</CODE><ACTIVE>1</ACTIVE></FLAG></FLAGS> <STOCK><AMOUNT>1</AMOUNT></STOCK><INFORMATION_PARAMETERS><INFORMATION_PARAMETER><NAME>Výkupní cena</NAME><VALUE>49 309 Kč</VALUE></INFORMATION_PARAMETER></INFORMATION_PARAMETERS><HEUREKA_HIDDEN>0</HEUREKA_HIDDEN><ZBOZI_HIDDEN>0</ZBOZI_HIDDEN><AVAILABILITY_IN_STOCK>Dodání 5-10 dní</AVAILABILITY_IN_STOCK><FREE_SHIPPING>1</FREE_SHIPPING></SHOPITEM>
  <SHOPITEM><CODE>MK0790</CODE><CURRENCY>CZK</CURRENCY><PRICE>26829</PRICE><FLAGS><FLAG><CODE>posledni-kus</CODE><ACTIVE>0</ACTIVE></FLAG><FLAG><CODE>trhem-overena-cena</CODE><ACTIVE>0</ACTIVE></FLAG></FLAGS> <STOCK><AMOUNT>5</AMOUNT></STOCK><INFORMATION_PARAMETERS><INFORMATION_PARAMETER><NAME>Výkupní cena</NAME><VALUE>26 212 Kč</VALUE></INFORMATION_PARAMETER></INFORMATION_PARAMETERS><HEUREKA_HIDDEN>1</HEUREKA_HIDDEN><ZBOZI_HIDDEN>1</ZBOZI_HIDDEN><AVAILABILITY_IN_STOCK>Dodání 5-10 dní</AVAILABILITY_IN_STOCK><FREE_SHIPPING>0</FREE_SHIPPING></SHOPITEM>
  <SHOPITEM><CODE>MK0789</CODE><CURRENCY>CZK</CURRENCY><PRICE>11128</PRICE><FLAGS><FLAG><CODE>posledni-kus</CODE><ACTIVE>0</ACTIVE></FLAG><FLAG><CODE>trhem-overena-cena</CODE><ACTIVE>1</ACTIVE></FLAG></FLAGS> <STOCK><AMOUNT>4</AMOUNT></STOCK><INFORMATION_PARAMETERS><INFORMATION_PARAMETER><NAME>Výkupní cena</NAME><VALUE>10 336 Kč</VALUE></INFORMATION_PARAMETER></INFORMATION_PARAMETERS><HEUREKA_HIDDEN>0</HEUREKA_HIDDEN><ZBOZI_HIDDEN>0</ZBOZI_HIDDEN><AVAILABILITY_IN_STOCK>Dodání 5-10 dní</AVAILABILITY_IN_STOCK><FREE_SHIPPING>0</FREE_SHIPPING></SHOPITEM>
  <SHOPITEM><CODE>MK0791</CODE><CURRENCY>CZK</CURRENCY><PRICE>6385</PRICE><FLAGS><FLAG><CODE>posledni-kus</CODE><ACTIVE>0</ACTIVE></FLAG><FLAG><CODE>trhem-overena-cena</CODE><ACTIVE>1</ACTIVE></FLAG></FLAGS> <STOCK><AMOUNT>6</AMOUNT></STOCK><INFORMATION_PARAMETERS><INFORMATION_PARAMETER><NAME>Výkupní cena</NAME><VALUE>4 911 Kč</VALUE></INFORMATION_PARAMETER></INFORMATION_PARAMETERS><HEUREKA_HIDDEN>0</HEUREKA_HIDDEN><ZBOZI_HIDDEN>0</ZBOZI_HIDDEN><AVAILABILITY_IN_STOCK>Dodání 5-10 dní</AVAILABILITY_IN_STOCK><FREE_SHIPPING>0</FREE_SHIPPING></SHOPITEM>
  <SHOPITEM><CODE>MK0792</CODE><CURRENCY>CZK</CURRENCY><PRICE>98611</PRICE><FLAGS><FLAG><CODE>posledni-kus</CODE><ACTIVE>0</ACTIVE></FLAG><FLAG><CODE>trhem-overena-cena</CODE><ACTIVE>0</ACTIVE></FLAG></FLAGS> <STOCK><AMOUNT>284</AMOUNT></STOCK><INFORMATION_PARAMETERS><INFORMATION_PARAMETER><NAME>Výkupní cena</NAME><VALUE>97 970 Kč</VALUE></INFORMATION_PARAMETER></INFORMATION_PARAMETERS><HEUREKA_HIDDEN>1</HEUREKA_HIDDEN><ZBOZI_HIDDEN>1</ZBOZI_HIDDEN><AVAILABILITY_IN_STOCK>Dodání 5-10 dní</AVAILABILITY_IN_STOCK><FREE_SHIPPING>1</FREE_SHIPPING></SHOPITEM>
  <SHOPITEM><CODE>MK0793</CODE><CURRENCY>CZK</CURRENCY><PRICE>51176</PRICE><FLAGS><FLAG><CODE>posledni-kus</CODE><ACTIVE>0</ACTIVE></FLAG><FLAG><CODE>trhem-overena-cena</CODE><ACTIVE>0</ACTIVE></FLAG></FLAGS> <STOCK><AMOUNT>103</AMOUNT></STOCK><INFORMATION_PARAMETERS><INFORMATION_PARAMETER><NAME>Výkupní cena</NAME><VALUE>50 964 Kč</VALUE></INFORMATION_PARAMETER></INFORMATION_PARAMETERS><HEUREKA_HIDDEN>1</HEUREKA_HIDDEN><ZBOZI_HIDDEN>1</ZBOZI_HIDDEN><AVAILABILITY_IN_STOCK>Dodání 5-10 dní</AVAILABILITY_IN_STOCK><FREE_SHIPPING>1</FREE_SHIPPING></SHOPITEM>
  <SHOPITEM><CODE>MK0794</CODE><CURRENCY>CZK</CURRENCY><PRICE>26076</PRICE><FLAGS><FLAG><CODE>posledni-kus</CODE><ACTIVE>0</ACTIVE></FLAG><FLAG><CODE>trhem-overena-cena</CODE><ACTIVE>0</ACTIVE></FLAG></FLAGS> <STOCK><AMOUNT>5</AMOUNT></STOCK><INFORMATION_PARAMETERS><INFORMATION_PARAMETER><NAME>Výkupní cena</NAME><VALUE>24 845 Kč</VALUE></INFORMATION_PARAMETER></INFORMATION_PARAMETERS><HEUREKA_HIDDEN>1</HEUREKA_HIDDEN><ZBOZI_HIDDEN>1</ZBOZI_HIDDEN><AVAILABILITY_IN_STOCK>Dodání 5-10 dní</AVAILABILITY_IN_STOCK><FREE_SHIPPING>0</FREE_SHIPPING></SHOPITEM>
  <SHOPITEM><CODE>MK0795</CODE><CURRENCY>CZK</CURRENCY><PRICE>10863</PRICE><FLAGS><FLAG><CODE>posledni-kus</CODE><ACTIVE>0</ACTIVE></FLAG><FLAG><CODE>trhem-overena-cena</CODE><ACTIVE>0</ACTIVE></FLAG></FLAGS> <STOCK><AMOUNT>5</AMOUNT></STOCK><INFORMATION_PARAMETERS><INFORMATION_PARAMETER><NAME>Výkupní cena</NAME><VALUE>9 447 Kč</VALUE></INFORMATION_PARAMETER></INFORMATION_PARAMETERS><HEUREKA_HIDDEN>1</HEUREKA_HIDDEN><ZBOZI_HIDDEN>1</ZBOZI_HIDDEN><AVAILABILITY_IN_STOCK>Skladem</AVAILABILITY_IN_STOCK><FREE_SHIPPING>0</FREE_SHIPPING></SHOPITEM>
  <SHOPITEM><CODE>MK0796</CODE><CURRENCY>CZK</CURRENCY><PRICE>3966</PRICE><FLAGS><FLAG><CODE>posledni-kus</CODE><ACTIVE>0</ACTIVE></FLAG><FLAG><CODE>trhem-overena-cena</CODE><ACTIVE>0</ACTIVE></FLAG></FLAGS> <STOCK><AMOUNT>5</AMOUNT></STOCK><INFORMATION_PARAMETERS><INFORMATION_PARAMETER><NAME>Výkupní cena</NAME><VALUE>3 107 Kč</VALUE></INFORMATION_PARAMETER></INFORMATION_PARAMETERS><HEUREKA_HIDDEN>1</HEUREKA_HIDDEN><ZBOZI_HIDDEN>1</ZBOZI_HIDDEN><AVAILABILITY_IN_STOCK>Skladem</AVAILABILITY_IN_STOCK><FREE_SHIPPING>0</FREE_SHIPPING></SHOPITEM>
  <SHOPITEM><CODE>MK0564</CODE><CURRENCY>CZK</CURRENCY><PRICE>3754</PRICE><FLAGS><FLAG><CODE>posledni-kus</CODE><ACTIVE>0</ACTIVE></FLAG><FLAG><CODE>trhem-overena-cena</CODE><ACTIVE>0</ACTIVE></FLAG></FLAGS> <STOCK><AMOUNT>5</AMOUNT></STOCK><INFORMATION_PARAMETERS><INFORMATION_PARAMETER><NAME>Výkupní cena</NAME><VALUE>3 245 Kč</VALUE></INFORMATION_PARAMETER></INFORMATION_PARAMETERS><HEUREKA_HIDDEN>1</HEUREKA_HIDDEN><ZBOZI_HIDDEN>1</ZBOZI_HIDDEN><AVAILABILITY_IN_STOCK>Skladem</AVAILABILITY_IN_STOCK><FREE_SHIPPING>0</FREE_SHIPPING></SHOPITEM>
  <SHOPITEM><CODE>MK0566</CODE><CURRENCY>CZK</CURRENCY><PRICE>17582</PRICE><FLAGS><FLAG><CODE>posledni-kus</CODE><ACTIVE>0</ACTIVE></FLAG><FLAG><CODE>trhem-overena-cena</CODE><ACTIVE>0</ACTIVE></FLAG></FLAGS> <STOCK><AMOUNT>5</AMOUNT></STOCK><INFORMATION_PARAMETERS><INFORMATION_PARAMETER><NAME>Výkupní cena</NAME><VALUE>16 369 Kč</VALUE></INFORMATION_PARAMETER></INFORMATION_PARAMETERS><HEUREKA_HIDDEN>1</HEUREKA_HIDDEN><ZBOZI_HIDDEN>1</ZBOZI_HIDDEN><AVAILABILITY_IN_STOCK>Skladem</AVAILABILITY_IN_STOCK><FREE_SHIPPING>0</FREE_SHIPPING></SHOPITEM>
  <SHOPITEM><CODE>MK0568</CODE><CURRENCY>CZK</CURRENCY><PRICE>66856</PRICE><FLAGS><FLAG><CODE>posledni-kus</CODE><ACTIVE>0</ACTIVE></FLAG><FLAG><CODE>trhem-overena-cena</CODE><ACTIVE>0</ACTIVE></FLAG></FLAGS> <STOCK><AMOUNT>5</AMOUNT></STOCK><INFORMATION_PARAMETERS><INFORMATION_PARAMETER><NAME>Výkupní cena</NAME><VALUE>63 490 Kč</VALUE></INFORMATION_PARAMETER></INFORMATION_PARAMETERS><HEUREKA_HIDDEN>1</HEUREKA_HIDDEN><ZBOZI_HIDDEN>1</ZBOZI_HIDDEN><AVAILABILITY_IN_STOCK>Skladem</AVAILABILITY_IN_STOCK><FREE_SHIPPING>1</FREE_SHIPPING></SHOPITEM>
  <SHOPITEM><CODE>MK0569</CODE><CURRENCY>CZK</CURRENCY><PRICE>102332</PRICE><FLAGS><FLAG><CODE>posledni-kus</CODE><ACTIVE>0</ACTIVE></FLAG><FLAG><CODE>trhem-overena-cena</CODE><ACTIVE>0</ACTIVE></FLAG></FLAGS> <STOCK><AMOUNT>5</AMOUNT></STOCK><INFORMATION_PARAMETERS><INFORMATION_PARAMETER><NAME>Výkupní cena</NAME><VALUE>98 628 Kč</VALUE></INFORMATION_PARAMETER></INFORMATION_PARAMETERS><HEUREKA_HIDDEN>1</HEUREKA_HIDDEN><ZBOZI_HIDDEN>1</ZBOZI_HIDDEN><AVAILABILITY_IN_STOCK>Skladem</AVAILABILITY_IN_STOCK><FREE_SHIPPING>1</FREE_SHIPPING></SHOPITEM>
  <SHOPITEM><CODE>MK0571</CODE><CURRENCY>CZK</CURRENCY><PRICE>333634</PRICE><FLAGS><FLAG><CODE>posledni-kus</CODE><ACTIVE>0</ACTIVE></FLAG><FLAG><CODE>trhem-overena-cena</CODE><ACTIVE>0</ACTIVE></FLAG></FLAGS> <STOCK><AMOUNT>5</AMOUNT></STOCK><INFORMATION_PARAMETERS><INFORMATION_PARAMETER><NAME>Výkupní cena</NAME><VALUE>305 270 Kč</VALUE></INFORMATION_PARAMETER></INFORMATION_PARAMETERS><HEUREKA_HIDDEN>1</HEUREKA_HIDDEN><ZBOZI_HIDDEN>1</ZBOZI_HIDDEN><AVAILABILITY_IN_STOCK>Skladem</AVAILABILITY_IN_STOCK><FREE_SHIPPING>1</FREE_SHIPPING></SHOPITEM>
  <SHOPITEM><CODE>MK0833</CODE><CURRENCY>CZK</CURRENCY><PRICE>9069</PRICE><FLAGS><FLAG><CODE>posledni-kus</CODE><ACTIVE>0</ACTIVE></FLAG><FLAG><CODE>trhem-overena-cena</CODE><ACTIVE>0</ACTIVE></FLAG></FLAGS> <STOCK><AMOUNT>5</AMOUNT></STOCK><INFORMATION_PARAMETERS><INFORMATION_PARAMETER><NAME>Výkupní cena</NAME><VALUE>8 494 Kč</VALUE></INFORMATION_PARAMETER></INFORMATION_PARAMETERS><HEUREKA_HIDDEN>1</HEUREKA_HIDDEN><ZBOZI_HIDDEN>1</ZBOZI_HIDDEN><AVAILABILITY_IN_STOCK>Skladem</AVAILABILITY_IN_STOCK><FREE_SHIPPING>0</FREE_SHIPPING></SHOPITEM>
  <SHOPITEM><CODE>MK0832</CODE><CURRENCY>CZK</CURRENCY><PRICE>34380</PRICE><FLAGS><FLAG><CODE>posledni-kus</CODE><ACTIVE>0</ACTIVE></FLAG><FLAG><CODE>trhem-overena-cena</CODE><ACTIVE>0</ACTIVE></FLAG></FLAGS> <STOCK><AMOUNT>5</AMOUNT></STOCK><INFORMATION_PARAMETERS><INFORMATION_PARAMETER><NAME>Výkupní cena</NAME><VALUE>32 177 Kč</VALUE></INFORMATION_PARAMETER></INFORMATION_PARAMETERS><HEUREKA_HIDDEN>1</HEUREKA_HIDDEN><ZBOZI_HIDDEN>1</ZBOZI_HIDDEN><AVAILABILITY_IN_STOCK>Skladem</AVAILABILITY_IN_STOCK><FREE_SHIPPING>0</FREE_SHIPPING></SHOPITEM>
  <SHOPITEM><CODE>MK0834</CODE><CURRENCY>CZK</CURRENCY><PRICE>67170</PRICE><FLAGS><FLAG><CODE>posledni-kus</CODE><ACTIVE>0</ACTIVE></FLAG><FLAG><CODE>trhem-overena-cena</CODE><ACTIVE>0</ACTIVE></FLAG></FLAGS> <STOCK><AMOUNT>5</AMOUNT></STOCK><INFORMATION_PARAMETERS><INFORMATION_PARAMETER><NAME>Výkupní cena</NAME><VALUE>63 968 Kč</VALUE></INFORMATION_PARAMETER></INFORMATION_PARAMETERS><HEUREKA_HIDDEN>1</HEUREKA_HIDDEN><ZBOZI_HIDDEN>1</ZBOZI_HIDDEN><AVAILABILITY_IN_STOCK>Skladem</AVAILABILITY_IN_STOCK><FREE_SHIPPING>1</FREE_SHIPPING></SHOPITEM>
  <SHOPITEM><CODE>MK0843</CODE><CURRENCY>CZK</CURRENCY><PRICE>102841</PRICE><FLAGS><FLAG><CODE>posledni-kus</CODE><ACTIVE>0</ACTIVE></FLAG><FLAG><CODE>trhem-overena-cena</CODE><ACTIVE>0</ACTIVE></FLAG></FLAGS> <STOCK><AMOUNT>5</AMOUNT></STOCK><INFORMATION_PARAMETERS><INFORMATION_PARAMETER><NAME>Výkupní cena</NAME><VALUE>94 862 Kč</VALUE></INFORMATION_PARAMETER></INFORMATION_PARAMETERS><HEUREKA_HIDDEN>1</HEUREKA_HIDDEN><ZBOZI_HIDDEN>1</ZBOZI_HIDDEN><AVAILABILITY_IN_STOCK>Skladem</AVAILABILITY_IN_STOCK><FREE_SHIPPING>1</FREE_SHIPPING></SHOPITEM>
  <SHOPITEM><CODE>MK0842</CODE><CURRENCY>CZK</CURRENCY><PRICE>168239</PRICE><FLAGS><FLAG><CODE>posledni-kus</CODE><ACTIVE>0</ACTIVE></FLAG><FLAG><CODE>trhem-overena-cena</CODE><ACTIVE>0</ACTIVE></FLAG></FLAGS> <STOCK><AMOUNT>5</AMOUNT></STOCK><INFORMATION_PARAMETERS><INFORMATION_PARAMETER><NAME>Výkupní cena</NAME><VALUE>159 478 Kč</VALUE></INFORMATION_PARAMETER></INFORMATION_PARAMETERS><HEUREKA_HIDDEN>1</HEUREKA_HIDDEN><ZBOZI_HIDDEN>1</ZBOZI_HIDDEN><AVAILABILITY_IN_STOCK>Skladem</AVAILABILITY_IN_STOCK><FREE_SHIPPING>1</FREE_SHIPPING></SHOPITEM>
  <SHOPITEM><CODE>MK0831</CODE><CURRENCY>CZK</CURRENCY><PRICE>335047</PRICE><FLAGS><FLAG><CODE>posledni-kus</CODE><ACTIVE>0</ACTIVE></FLAG><FLAG><CODE>trhem-overena-cena</CODE><ACTIVE>0</ACTIVE></FLAG></FLAGS> <STOCK><AMOUNT>5</AMOUNT></STOCK><INFORMATION_PARAMETERS><INFORMATION_PARAMETER><NAME>Výkupní cena</NAME><VALUE>322 964 Kč</VALUE></INFORMATION_PARAMETER></INFORMATION_PARAMETERS><HEUREKA_HIDDEN>1</HEUREKA_HIDDEN><ZBOZI_HIDDEN>1</ZBOZI_HIDDEN><AVAILABILITY_IN_STOCK>Dodání 5-10 dní</AVAILABILITY_IN_STOCK><FREE_SHIPPING>1</FREE_SHIPPING></SHOPITEM>
  <SHOPITEM><CODE>MK0700</CODE><CURRENCY>CZK</CURRENCY><PRICE>2386</PRICE><FLAGS><FLAG><CODE>posledni-kus</CODE><ACTIVE>0</ACTIVE></FLAG><FLAG><CODE>trhem-overena-cena</CODE><ACTIVE>0</ACTIVE></FLAG></FLAGS> <STOCK><AMOUNT>5</AMOUNT></STOCK><INFORMATION_PARAMETERS><INFORMATION_PARAMETER><NAME>Výkupní cena</NAME><VALUE>1 592 Kč</VALUE></INFORMATION_PARAMETER></INFORMATION_PARAMETERS><HEUREKA_HIDDEN>1</HEUREKA_HIDDEN><ZBOZI_HIDDEN>1</ZBOZI_HIDDEN><AVAILABILITY_IN_STOCK>Dodání 5-10 dní</AVAILABILITY_IN_STOCK><FREE_SHIPPING>0</FREE_SHIPPING></SHOPITEM>
  <SHOPITEM><CODE>MK0773</CODE><CURRENCY>CZK</CURRENCY><PRICE>2467</PRICE><FLAGS><FLAG><CODE>posledni-kus</CODE><ACTIVE>0</ACTIVE></FLAG><FLAG><CODE>trhem-overena-cena</CODE><ACTIVE>0</ACTIVE></FLAG></FLAGS> <STOCK><AMOUNT>3205</AMOUNT></STOCK><INFORMATION_PARAMETERS><INFORMATION_PARAMETER><NAME>Výkupní cena</NAME><VALUE>97 337 Kč</VALUE></INFORMATION_PARAMETER></INFORMATION_PARAMETERS><HEUREKA_HIDDEN>1</HEUREKA_HIDDEN><ZBOZI_HIDDEN>1</ZBOZI_HIDDEN><AVAILABILITY_IN_STOCK>Dodání 5-10 dní</AVAILABILITY_IN_STOCK><FREE_SHIPPING>0</FREE_SHIPPING></SHOPITEM>
  <SHOPITEM><CODE>MK0806</CODE><CURRENCY>CZK</CURRENCY><PRICE>44612</PRICE><STANDARD_PRICE>49340</STANDARD_PRICE><FLAGS><FLAG><CODE>posledni-kus</CODE><ACTIVE>0</ACTIVE></FLAG><FLAG><CODE>trhem-overena-cena</CODE><ACTIVE>1</ACTIVE></FLAG></FLAGS> <STOCK><AMOUNT>160</AMOUNT></STOCK><INFORMATION_PARAMETERS><INFORMATION_PARAMETER><NAME>Výkupní cena</NAME><VALUE>35 753 Kč</VALUE></INFORMATION_PARAMETER></INFORMATION_PARAMETERS><HEUREKA_HIDDEN>0</HEUREKA_HIDDEN><ZBOZI_HIDDEN>0</ZBOZI_HIDDEN><AVAILABILITY_IN_STOCK>Dodání 5-10 dní</AVAILABILITY_IN_STOCK><FREE_SHIPPING>1</FREE_SHIPPING></SHOPITEM>
  <SHOPITEM><CODE>MK0807</CODE><CURRENCY>CZK</CURRENCY><PRICE>1093846</PRICE><STANDARD_PRICE>1233500</STANDARD_PRICE><FLAGS><FLAG><CODE>posledni-kus</CODE><ACTIVE>0</ACTIVE></FLAG><FLAG><CODE>trhem-overena-cena</CODE><ACTIVE>1</ACTIVE></FLAG></FLAGS> <STOCK><AMOUNT>6</AMOUNT></STOCK><INFORMATION_PARAMETERS><INFORMATION_PARAMETER><NAME>Výkupní cena</NAME><VALUE>922 054 Kč</VALUE></INFORMATION_PARAMETER></INFORMATION_PARAMETERS><HEUREKA_HIDDEN>0</HEUREKA_HIDDEN><ZBOZI_HIDDEN>0</ZBOZI_HIDDEN><AVAILABILITY_IN_STOCK>Dodání 5-10 dní</AVAILABILITY_IN_STOCK><FREE_SHIPPING>1</FREE_SHIPPING></SHOPITEM>
  <SHOPITEM><CODE>MK0742</CODE><CURRENCY>CZK</CURRENCY><PRICE>2467</PRICE><FLAGS><FLAG><CODE>posledni-kus</CODE><ACTIVE>0</ACTIVE></FLAG><FLAG><CODE>trhem-overena-cena</CODE><ACTIVE>0</ACTIVE></FLAG></FLAGS> <STOCK><AMOUNT>5</AMOUNT></STOCK><INFORMATION_PARAMETERS><INFORMATION_PARAMETER><NAME>Výkupní cena</NAME><VALUE>2 023 Kč</VALUE></INFORMATION_PARAMETER></INFORMATION_PARAMETERS><HEUREKA_HIDDEN>1</HEUREKA_HIDDEN><ZBOZI_HIDDEN>1</ZBOZI_HIDDEN><AVAILABILITY_IN_STOCK>Skladem</AVAILABILITY_IN_STOCK><FREE_SHIPPING>0</FREE_SHIPPING></SHOPITEM>
  <SHOPITEM><CODE>MK0804</CODE><CURRENCY>CZK</CURRENCY><PRICE>55765</PRICE><STANDARD_PRICE>61675</STANDARD_PRICE><FLAGS><FLAG><CODE>posledni-kus</CODE><ACTIVE>0</ACTIVE></FLAG><FLAG><CODE>trhem-overena-cena</CODE><ACTIVE>1</ACTIVE></FLAG></FLAGS> <STOCK><AMOUNT>392</AMOUNT></STOCK><INFORMATION_PARAMETERS><INFORMATION_PARAMETER><NAME>Výkupní cena</NAME><VALUE>45 445 Kč</VALUE></INFORMATION_PARAMETER></INFORMATION_PARAMETERS><HEUREKA_HIDDEN>0</HEUREKA_HIDDEN><ZBOZI_HIDDEN>0</ZBOZI_HIDDEN><AVAILABILITY_IN_STOCK>Dodání 5-10 dní</AVAILABILITY_IN_STOCK><FREE_SHIPPING>1</FREE_SHIPPING></SHOPITEM>
  <SHOPITEM><CODE>MK0805</CODE><CURRENCY>CZK</CURRENCY><PRICE>1093846</PRICE><STANDARD_PRICE>1233500</STANDARD_PRICE><FLAGS><FLAG><CODE>posledni-kus</CODE><ACTIVE>0</ACTIVE></FLAG><FLAG><CODE>trhem-overena-cena</CODE><ACTIVE>1</ACTIVE></FLAG></FLAGS> <STOCK><AMOUNT>19</AMOUNT></STOCK><INFORMATION_PARAMETERS><INFORMATION_PARAMETER><NAME>Výkupní cena</NAME><VALUE>927 827 Kč</VALUE></INFORMATION_PARAMETER></INFORMATION_PARAMETERS><HEUREKA_HIDDEN>0</HEUREKA_HIDDEN><ZBOZI_HIDDEN>0</ZBOZI_HIDDEN><AVAILABILITY_IN_STOCK>Dodání 5-10 dní</AVAILABILITY_IN_STOCK><FREE_SHIPPING>1</FREE_SHIPPING></SHOPITEM>
  <SHOPITEM><CODE>MK0743</CODE><CURRENCY>CZK</CURRENCY><PRICE>2706</PRICE><FLAGS><FLAG><CODE>posledni-kus</CODE><ACTIVE>0</ACTIVE></FLAG><FLAG><CODE>trhem-overena-cena</CODE><ACTIVE>0</ACTIVE></FLAG></FLAGS> <STOCK><AMOUNT>5</AMOUNT></STOCK><INFORMATION_PARAMETERS><INFORMATION_PARAMETER><NAME>Výkupní cena</NAME><VALUE>1 654 Kč</VALUE></INFORMATION_PARAMETER></INFORMATION_PARAMETERS><HEUREKA_HIDDEN>1</HEUREKA_HIDDEN><ZBOZI_HIDDEN>1</ZBOZI_HIDDEN><AVAILABILITY_IN_STOCK>Skladem</AVAILABILITY_IN_STOCK><FREE_SHIPPING>0</FREE_SHIPPING></SHOPITEM>
  <SHOPITEM><CODE>MK0808</CODE><CURRENCY>CZK</CURRENCY><PRICE>2707</PRICE><FLAGS><FLAG><CODE>posledni-kus</CODE><ACTIVE>0</ACTIVE></FLAG><FLAG><CODE>trhem-overena-cena</CODE><ACTIVE>0</ACTIVE></FLAG></FLAGS> <STOCK><AMOUNT>5</AMOUNT></STOCK><INFORMATION_PARAMETERS><INFORMATION_PARAMETER><NAME>Výkupní cena</NAME><VALUE>1 747 Kč</VALUE></INFORMATION_PARAMETER></INFORMATION_PARAMETERS><HEUREKA_HIDDEN>1</HEUREKA_HIDDEN><ZBOZI_HIDDEN>1</ZBOZI_HIDDEN><AVAILABILITY_IN_STOCK>Skladem</AVAILABILITY_IN_STOCK><FREE_SHIPPING>0</FREE_SHIPPING></SHOPITEM>
  <SHOPITEM><CODE>MK0803</CODE><CURRENCY>CZK</CURRENCY><PRICE>2382</PRICE><FLAGS><FLAG><CODE>posledni-kus</CODE><ACTIVE>0</ACTIVE></FLAG><FLAG><CODE>trhem-overena-cena</CODE><ACTIVE>0</ACTIVE></FLAG></FLAGS> <STOCK><AMOUNT>5</AMOUNT></STOCK><INFORMATION_PARAMETERS><INFORMATION_PARAMETER><NAME>Výkupní cena</NAME><VALUE>1 525 Kč</VALUE></INFORMATION_PARAMETER></INFORMATION_PARAMETERS><HEUREKA_HIDDEN>1</HEUREKA_HIDDEN><ZBOZI_HIDDEN>1</ZBOZI_HIDDEN><AVAILABILITY_IN_STOCK>Dodání 5-10 dní</AVAILABILITY_IN_STOCK><FREE_SHIPPING>0</FREE_SHIPPING></SHOPITEM>
  <SHOPITEM><CODE>MK0811</CODE><CURRENCY>CZK</CURRENCY><PRICE>1084446</PRICE><STANDARD_PRICE>1191000</STANDARD_PRICE><FLAGS><FLAG><CODE>posledni-kus</CODE><ACTIVE>0</ACTIVE></FLAG><FLAG><CODE>trhem-overena-cena</CODE><ACTIVE>0</ACTIVE></FLAG></FLAGS> <STOCK><AMOUNT>0</AMOUNT></STOCK><INFORMATION_PARAMETERS><INFORMATION_PARAMETER><NAME>Výkupní cena</NAME><VALUE>881 782 Kč</VALUE></INFORMATION_PARAMETER></INFORMATION_PARAMETERS><HEUREKA_HIDDEN>0</HEUREKA_HIDDEN><ZBOZI_HIDDEN>0</ZBOZI_HIDDEN><AVAILABILITY_IN_STOCK>Dodání 5-10 dní</AVAILABILITY_IN_STOCK><FREE_SHIPPING>0</FREE_SHIPPING></SHOPITEM>
  <SHOPITEM><CODE>MK0578</CODE><CURRENCY>CZK</CURRENCY><PRICE>3067</PRICE><FLAGS><FLAG><CODE>posledni-kus</CODE><ACTIVE>0</ACTIVE></FLAG><FLAG><CODE>trhem-overena-cena</CODE><ACTIVE>0</ACTIVE></FLAG></FLAGS> <STOCK><AMOUNT>5</AMOUNT></STOCK><INFORMATION_PARAMETERS><INFORMATION_PARAMETER><NAME>Výkupní cena</NAME><VALUE>884 Kč</VALUE></INFORMATION_PARAMETER></INFORMATION_PARAMETERS><HEUREKA_HIDDEN>1</HEUREKA_HIDDEN><ZBOZI_HIDDEN>1</ZBOZI_HIDDEN><AVAILABILITY_IN_STOCK>Dodání 5-10 dní</AVAILABILITY_IN_STOCK><FREE_SHIPPING>0</FREE_SHIPPING></SHOPITEM>
  <SHOPITEM><CODE>MK0689</CODE><CURRENCY>CZK</CURRENCY><PRICE>3942</PRICE><FLAGS><FLAG><CODE>posledni-kus</CODE><ACTIVE>0</ACTIVE></FLAG><FLAG><CODE>trhem-overena-cena</CODE><ACTIVE>0</ACTIVE></FLAG></FLAGS> <STOCK><AMOUNT>5</AMOUNT></STOCK><INFORMATION_PARAMETERS><INFORMATION_PARAMETER><NAME>Výkupní cena</NAME><VALUE>1 529 Kč</VALUE></INFORMATION_PARAMETER></INFORMATION_PARAMETERS><HEUREKA_HIDDEN>1</HEUREKA_HIDDEN><ZBOZI_HIDDEN>1</ZBOZI_HIDDEN><AVAILABILITY_IN_STOCK>Dodání 5-10 dní</AVAILABILITY_IN_STOCK><FREE_SHIPPING>0</FREE_SHIPPING></SHOPITEM>
  <SHOPITEM><CODE>MK0581</CODE><CURRENCY>CZK</CURRENCY><PRICE>19654</PRICE><FLAGS><FLAG><CODE>posledni-kus</CODE><ACTIVE>0</ACTIVE></FLAG><FLAG><CODE>trhem-overena-cena</CODE><ACTIVE>1</ACTIVE></FLAG></FLAGS> <STOCK><AMOUNT>95</AMOUNT></STOCK><INFORMATION_PARAMETERS><INFORMATION_PARAMETER><NAME>Výkupní cena</NAME><VALUE>13 226 Kč</VALUE></INFORMATION_PARAMETER></INFORMATION_PARAMETERS><HEUREKA_HIDDEN>0</HEUREKA_HIDDEN><ZBOZI_HIDDEN>0</ZBOZI_HIDDEN><AVAILABILITY_IN_STOCK>Dodání 5-10 dní</AVAILABILITY_IN_STOCK><FREE_SHIPPING>1</FREE_SHIPPING></SHOPITEM>
  <SHOPITEM><CODE>MK0582</CODE><CURRENCY>CZK</CURRENCY><PRICE>36106</PRICE><FLAGS><FLAG><CODE>posledni-kus</CODE><ACTIVE>0</ACTIVE></FLAG><FLAG><CODE>trhem-overena-cena</CODE><ACTIVE>1</ACTIVE></FLAG></FLAGS> <STOCK><AMOUNT>215</AMOUNT></STOCK><INFORMATION_PARAMETERS><INFORMATION_PARAMETER><NAME>Výkupní cena</NAME><VALUE>24 499 Kč</VALUE></INFORMATION_PARAMETER></INFORMATION_PARAMETERS><HEUREKA_HIDDEN>0</HEUREKA_HIDDEN><ZBOZI_HIDDEN>0</ZBOZI_HIDDEN><AVAILABILITY_IN_STOCK>Dodání 5-10 dní</AVAILABILITY_IN_STOCK><FREE_SHIPPING>1</FREE_SHIPPING></SHOPITEM>
  <SHOPITEM><CODE>MK0583</CODE><CURRENCY>CZK</CURRENCY><PRICE>68245</PRICE><FLAGS><FLAG><CODE>posledni-kus</CODE><ACTIVE>0</ACTIVE></FLAG><FLAG><CODE>trhem-overena-cena</CODE><ACTIVE>0</ACTIVE></FLAG></FLAGS> <STOCK><AMOUNT>242</AMOUNT></STOCK><INFORMATION_PARAMETERS><INFORMATION_PARAMETER><NAME>Výkupní cena</NAME><VALUE>66 968 Kč</VALUE></INFORMATION_PARAMETER></INFORMATION_PARAMETERS><HEUREKA_HIDDEN>1</HEUREKA_HIDDEN><ZBOZI_HIDDEN>1</ZBOZI_HIDDEN><AVAILABILITY_IN_STOCK>Dodání 5-10 dní</AVAILABILITY_IN_STOCK><FREE_SHIPPING>1</FREE_SHIPPING></SHOPITEM>
  <SHOPITEM><CODE>MK0584</CODE><CURRENCY>CZK</CURRENCY><PRICE>385412</PRICE><FLAGS><FLAG><CODE>posledni-kus</CODE><ACTIVE>0</ACTIVE></FLAG><FLAG><CODE>trhem-overena-cena</CODE><ACTIVE>0</ACTIVE></FLAG></FLAGS> <STOCK><AMOUNT>5</AMOUNT></STOCK><INFORMATION_PARAMETERS><INFORMATION_PARAMETER><NAME>Výkupní cena</NAME><VALUE>204 964 Kč</VALUE></INFORMATION_PARAMETER></INFORMATION_PARAMETERS><HEUREKA_HIDDEN>1</HEUREKA_HIDDEN><ZBOZI_HIDDEN>1</ZBOZI_HIDDEN><AVAILABILITY_IN_STOCK>Dodání 5-10 dní</AVAILABILITY_IN_STOCK><FREE_SHIPPING>1</FREE_SHIPPING></SHOPITEM>
  <SHOPITEM><CODE>MK0585</CODE><CURRENCY>CZK</CURRENCY><PRICE>1104331</PRICE><FLAGS><FLAG><CODE>posledni-kus</CODE><ACTIVE>0</ACTIVE></FLAG><FLAG><CODE>trhem-overena-cena</CODE><ACTIVE>0</ACTIVE></FLAG></FLAGS> <STOCK><AMOUNT>5</AMOUNT></STOCK><INFORMATION_PARAMETERS><INFORMATION_PARAMETER><NAME>Výkupní cena</NAME><VALUE>873 819 Kč</VALUE></INFORMATION_PARAMETER></INFORMATION_PARAMETERS><HEUREKA_HIDDEN>1</HEUREKA_HIDDEN><ZBOZI_HIDDEN>1</ZBOZI_HIDDEN><AVAILABILITY_IN_STOCK>Dodání 5-10 dní</AVAILABILITY_IN_STOCK><FREE_SHIPPING>1</FREE_SHIPPING></SHOPITEM>
  <SHOPITEM><CODE>MK0844</CODE><CURRENCY>CZK</CURRENCY><PRICE>2835</PRICE><FLAGS><FLAG><CODE>posledni-kus</CODE><ACTIVE>0</ACTIVE></FLAG><FLAG><CODE>trhem-overena-cena</CODE><ACTIVE>0</ACTIVE></FLAG></FLAGS> <STOCK><AMOUNT>5</AMOUNT></STOCK><INFORMATION_PARAMETERS><INFORMATION_PARAMETER><NAME>Výkupní cena</NAME><VALUE>1 376 Kč</VALUE></INFORMATION_PARAMETER></INFORMATION_PARAMETERS><HEUREKA_HIDDEN>1</HEUREKA_HIDDEN><ZBOZI_HIDDEN>1</ZBOZI_HIDDEN><AVAILABILITY_IN_STOCK>Skladem</AVAILABILITY_IN_STOCK><FREE_SHIPPING>0</FREE_SHIPPING></SHOPITEM>
  <SHOPITEM><CODE>MK0845</CODE><CURRENCY>CZK</CURRENCY><PRICE>4802</PRICE><FLAGS><FLAG><CODE>posledni-kus</CODE><ACTIVE>0</ACTIVE></FLAG><FLAG><CODE>trhem-overena-cena</CODE><ACTIVE>0</ACTIVE></FLAG></FLAGS> <STOCK><AMOUNT>5</AMOUNT></STOCK><INFORMATION_PARAMETERS><INFORMATION_PARAMETER><NAME>Výkupní cena</NAME><VALUE>3 143 Kč</VALUE></INFORMATION_PARAMETER></INFORMATION_PARAMETERS><HEUREKA_HIDDEN>1</HEUREKA_HIDDEN><ZBOZI_HIDDEN>1</ZBOZI_HIDDEN><AVAILABILITY_IN_STOCK>Dodání do 15 dní</AVAILABILITY_IN_STOCK><FREE_SHIPPING>0</FREE_SHIPPING></SHOPITEM>
  <SHOPITEM><CODE>MK0701</CODE><CURRENCY>CZK</CURRENCY><PRICE>4990</PRICE><FLAGS><FLAG><CODE>posledni-kus</CODE><ACTIVE>0</ACTIVE></FLAG><FLAG><CODE>trhem-overena-cena</CODE><ACTIVE>0</ACTIVE></FLAG></FLAGS> <STOCK><AMOUNT>5</AMOUNT></STOCK><INFORMATION_PARAMETERS><INFORMATION_PARAMETER><NAME>Výkupní cena</NAME><VALUE>3 040 Kč</VALUE></INFORMATION_PARAMETER></INFORMATION_PARAMETERS><HEUREKA_HIDDEN>1</HEUREKA_HIDDEN><ZBOZI_HIDDEN>1</ZBOZI_HIDDEN><AVAILABILITY_IN_STOCK>Skladem</AVAILABILITY_IN_STOCK><FREE_SHIPPING>0</FREE_SHIPPING></SHOPITEM>
  <SHOPITEM><CODE>MK0702</CODE><CURRENCY>CZK</CURRENCY><PRICE>60436</PRICE><FLAGS><FLAG><CODE>posledni-kus</CODE><ACTIVE>0</ACTIVE></FLAG><FLAG><CODE>trhem-overena-cena</CODE><ACTIVE>1</ACTIVE></FLAG></FLAGS> <STOCK><AMOUNT>16</AMOUNT></STOCK><INFORMATION_PARAMETERS><INFORMATION_PARAMETER><NAME>Výkupní cena</NAME><VALUE>49 458 Kč</VALUE></INFORMATION_PARAMETER></INFORMATION_PARAMETERS><HEUREKA_HIDDEN>0</HEUREKA_HIDDEN><ZBOZI_HIDDEN>0</ZBOZI_HIDDEN><AVAILABILITY_IN_STOCK>Dodání 5-10 dní</AVAILABILITY_IN_STOCK><FREE_SHIPPING>1</FREE_SHIPPING></SHOPITEM>
  <SHOPITEM><CODE>MK0797</CODE><CURRENCY>CZK</CURRENCY><PRICE>60288</PRICE><FLAGS><FLAG><CODE>posledni-kus</CODE><ACTIVE>0</ACTIVE></FLAG><FLAG><CODE>trhem-overena-cena</CODE><ACTIVE>1</ACTIVE></FLAG></FLAGS> <STOCK><AMOUNT>24</AMOUNT></STOCK><INFORMATION_PARAMETERS><INFORMATION_PARAMETER><NAME>Výkupní cena</NAME><VALUE>46 041 Kč</VALUE></INFORMATION_PARAMETER></INFORMATION_PARAMETERS><HEUREKA_HIDDEN>0</HEUREKA_HIDDEN><ZBOZI_HIDDEN>0</ZBOZI_HIDDEN><AVAILABILITY_IN_STOCK>Dodání 5-10 dní</AVAILABILITY_IN_STOCK><FREE_SHIPPING>1</FREE_SHIPPING></SHOPITEM>
  <SHOPITEM><CODE>MK0798</CODE><CURRENCY>CZK</CURRENCY><PRICE>32154</PRICE><FLAGS><FLAG><CODE>posledni-kus</CODE><ACTIVE>0</ACTIVE></FLAG><FLAG><CODE>trhem-overena-cena</CODE><ACTIVE>0</ACTIVE></FLAG></FLAGS> <STOCK><AMOUNT>0</AMOUNT></STOCK><INFORMATION_PARAMETERS><INFORMATION_PARAMETER><NAME>Výkupní cena</NAME><VALUE>22 643 Kč</VALUE></INFORMATION_PARAMETER></INFORMATION_PARAMETERS><HEUREKA_HIDDEN>0</HEUREKA_HIDDEN><ZBOZI_HIDDEN>0</ZBOZI_HIDDEN><AVAILABILITY_IN_STOCK>Dodání 5-10 dní</AVAILABILITY_IN_STOCK><FREE_SHIPPING>0</FREE_SHIPPING></SHOPITEM>
  <SHOPITEM><CODE>MK0799</CODE><CURRENCY>CZK</CURRENCY><PRICE>16482</PRICE><FLAGS><FLAG><CODE>posledni-kus</CODE><ACTIVE>0</ACTIVE></FLAG><FLAG><CODE>trhem-overena-cena</CODE><ACTIVE>0</ACTIVE></FLAG></FLAGS> <STOCK><AMOUNT>0</AMOUNT></STOCK><INFORMATION_PARAMETERS><INFORMATION_PARAMETER><NAME>Výkupní cena</NAME><VALUE>11 056 Kč</VALUE></INFORMATION_PARAMETER></INFORMATION_PARAMETERS><HEUREKA_HIDDEN>0</HEUREKA_HIDDEN><ZBOZI_HIDDEN>0</ZBOZI_HIDDEN><AVAILABILITY_IN_STOCK>Dodání 5-10 dní</AVAILABILITY_IN_STOCK><FREE_SHIPPING>0</FREE_SHIPPING></SHOPITEM>
  <SHOPITEM><CODE>MK0800</CODE><CURRENCY>CZK</CURRENCY><PRICE>61946</PRICE><FLAGS><FLAG><CODE>posledni-kus</CODE><ACTIVE>0</ACTIVE></FLAG><FLAG><CODE>trhem-overena-cena</CODE><ACTIVE>0</ACTIVE></FLAG></FLAGS> <STOCK><AMOUNT>0</AMOUNT></STOCK><INFORMATION_PARAMETERS><INFORMATION_PARAMETER><NAME>Výkupní cena</NAME><VALUE>46 041 Kč</VALUE></INFORMATION_PARAMETER></INFORMATION_PARAMETERS><HEUREKA_HIDDEN>0</HEUREKA_HIDDEN><ZBOZI_HIDDEN>0</ZBOZI_HIDDEN><AVAILABILITY_IN_STOCK>Dodání 5-10 dní</AVAILABILITY_IN_STOCK><FREE_SHIPPING>0</FREE_SHIPPING></SHOPITEM>
  <SHOPITEM><CODE>MK0801</CODE><CURRENCY>CZK</CURRENCY><PRICE>61946</PRICE><FLAGS><FLAG><CODE>posledni-kus</CODE><ACTIVE>0</ACTIVE></FLAG><FLAG><CODE>trhem-overena-cena</CODE><ACTIVE>0</ACTIVE></FLAG></FLAGS> <STOCK><AMOUNT>0</AMOUNT></STOCK><INFORMATION_PARAMETERS><INFORMATION_PARAMETER><NAME>Výkupní cena</NAME><VALUE>46 041 Kč</VALUE></INFORMATION_PARAMETER></INFORMATION_PARAMETERS><HEUREKA_HIDDEN>0</HEUREKA_HIDDEN><ZBOZI_HIDDEN>0</ZBOZI_HIDDEN><AVAILABILITY_IN_STOCK>Dodání 5-10 dní</AVAILABILITY_IN_STOCK><FREE_SHIPPING>0</FREE_SHIPPING></SHOPITEM>
  <SHOPITEM><CODE>MK0693</CODE><CURRENCY>CZK</CURRENCY><PRICE>65467</PRICE><FLAGS><FLAG><CODE>posledni-kus</CODE><ACTIVE>0</ACTIVE></FLAG><FLAG><CODE>trhem-overena-cena</CODE><ACTIVE>0</ACTIVE></FLAG></FLAGS> <STOCK><AMOUNT>5</AMOUNT></STOCK><INFORMATION_PARAMETERS><INFORMATION_PARAMETER><NAME>Výkupní cena</NAME><VALUE>42 903 Kč</VALUE></INFORMATION_PARAMETER></INFORMATION_PARAMETERS><HEUREKA_HIDDEN>1</HEUREKA_HIDDEN><ZBOZI_HIDDEN>1</ZBOZI_HIDDEN><AVAILABILITY_IN_STOCK>Dodání 5-10 dní</AVAILABILITY_IN_STOCK><FREE_SHIPPING>1</FREE_SHIPPING></SHOPITEM>
  <SHOPITEM><CODE>MK0690</CODE><CURRENCY>CZK</CURRENCY><PRICE>2719</PRICE><FLAGS><FLAG><CODE>posledni-kus</CODE><ACTIVE>0</ACTIVE></FLAG><FLAG><CODE>trhem-overena-cena</CODE><ACTIVE>0</ACTIVE></FLAG></FLAGS> <STOCK><AMOUNT>5</AMOUNT></STOCK><INFORMATION_PARAMETERS><INFORMATION_PARAMETER><NAME>Výkupní cena</NAME><VALUE>1 508 Kč</VALUE></INFORMATION_PARAMETER></INFORMATION_PARAMETERS><HEUREKA_HIDDEN>1</HEUREKA_HIDDEN><ZBOZI_HIDDEN>1</ZBOZI_HIDDEN><AVAILABILITY_IN_STOCK>Skladem</AVAILABILITY_IN_STOCK><FREE_SHIPPING>0</FREE_SHIPPING></SHOPITEM>
  <SHOPITEM><CODE>MK0691</CODE><CURRENCY>CZK</CURRENCY><PRICE>47602</PRICE><FLAGS><FLAG><CODE>posledni-kus</CODE><ACTIVE>0</ACTIVE></FLAG><FLAG><CODE>trhem-overena-cena</CODE><ACTIVE>0</ACTIVE></FLAG></FLAGS> <STOCK><AMOUNT>5</AMOUNT></STOCK><INFORMATION_PARAMETERS><INFORMATION_PARAMETER><NAME>Výkupní cena</NAME><VALUE>30 136 Kč</VALUE></INFORMATION_PARAMETER></INFORMATION_PARAMETERS><HEUREKA_HIDDEN>1</HEUREKA_HIDDEN><ZBOZI_HIDDEN>1</ZBOZI_HIDDEN><AVAILABILITY_IN_STOCK>Skladem</AVAILABILITY_IN_STOCK><FREE_SHIPPING>1</FREE_SHIPPING></SHOPITEM>
</SHOP>